axi4/axi4lite_slave.v
/*

File: axi4lite_slave.v
Description: AXI4 lite slave interface to handle data 
    reads and writes in the Network interface. The interface allows for a 
    more general protocol to access the FIFO buffers used for reads and writes 
    in the NI. 



*/

module axi4lite_slave(
    
    input wire aclk,
    input wire arestn,
    
    // read address channel
    input wire [31:0] araddr,
    input wire arvalid,
    output reg arready,

    // read data channel
    output wire [31:0] rdata,
    output wire [1:0] rresp,
    output reg rvalid,
    input wire rready,

    // write address channel
    input wire [31:0] awaddr,
    input wire awvalid,
    output reg awready,

    // write data channel
    input wire [31:0] wdata,
    input wire wvalid,
    output wire wready,

    // write response
    output wire [1:0] bresp,
    output reg bvalid, 
    input wire bready,
    
    // For fifo access
    output wire read_en,
    input wire [31:0] read_data,
    input wire empty,

    output wire write_en,
    output wire [63:0] write_data,
    input wire full

);

    // rresp or bresp
    // 0b00 - OKAY
    // 0b01 - EXOKAY
    // 0b10 - SLVERR
    // 0b11 - DECERR

    /* Hanlding Write operation from Master

    - Master Puts data and address and asserts AWVALID, WVALID, BREADY
    - Slave asserts AWREADY and WRREADY when ready to accept. Master deasserts valid and ready on bothe address and data
    - ASsert BVALID 
    - Deassert both in BVALID and BREADY are high

    */

    /* Handling Read operation from Master

    - Read address, ARVALID, RREADY from master.
    - ARREADY by slave
    - ARVALID and ARREADY deasserted 
    - puts requested data on bus and RVALID
    - Since both RREADY and RVALID , deasserted

    */

    assign	reset = !arestn;
    assign	wready = awready;

    assign rresp = 2'b00;
    assign bresp = 2'b00;

    assign write_en = bvalid; 
    assign read_en = rvalid;

    initial	awready = 1'b0;
    initial	bvalid = 1'b0;
    initial rvalid = 1'b0;
    initial arready = 1'b0;

    assign write_data = {awaddr, wdata};
    assign rdata =  read_data;
    
    // assign arready = arvalid;

    // write operation
    always @ (posedge aclk)begin

        if(reset)
        begin
            bvalid <= 1'b0;
            // Clear FIFO
        end
        else if(wready)begin
            // write to FIFO        
            bvalid <= 1'b1;
        end
        else if(bready)//!bvalid
            bvalid <= 1'b0;
        
    end
    
    always @(posedge aclk)begin
        if(reset)
            awready <= 1'b0;
        else 
            awready <= !awready 
            && (awvalid && wvalid)
            && (!bvalid || bready);
    end


    // read operation 
    always@(posedge aclk)begin
        if (reset)begin
            arready =1'b0;
            rvalid <=1'b0; 
        end
        if (arvalid && !arready)
            arready <= 1'b1;
        if (arready)begin
            arready <= 1'b0;
            rvalid <=1'b1;
        end
        if (rready && rvalid)begin
            rvalid <= 1'b0;
        end
    end
    


/*
Instead of registers we are using fifo 
disregards address as reg address or fifo address. 
Can we use address to append to data and use the whole thing
to be stored in the fifo

Leaving strobe write out for this implementation

*/

endmodule

tb/axi4/axi4lite_slave_tb.v
`timescale 1ns / 1ps
`include "../../axi4/axi4lite_slave.v"

/*

timing checks on 
https://www.realdigital.org/doc/a9fee931f7a172423e1ba73f66ca4081


*/
module axi4lite_slave_tb();
    
    reg clk;
    reg arestn;
    
    // read address channel
    reg [31:0] araddr;
    reg arvalid;
    wire arready;

    // read data channel
    wire [31:0] rdata;
    wire [1:0] rresp;
    wire rvalid;
    reg rready;

    // write address channel
    reg [31:0] awaddr;
    reg awvalid;
    wire awready;

    // write data channel
    reg [31:0] wdata;
    reg wvalid;
    wire wready;

    // write response
    wire [1:0] bresp;
    wire bvalid; 
    reg bready;
    
    // fifo 
    wire read_en;
    reg [31:0] read_data;
    reg empty;

    wire write_en;
    wire [63:0] write_data;
    reg full;

    // Instantiate the FIFO module
    axi4lite_slave my_slave (
        clk,
        arestn,
        araddr,
        arvalid,
        arready,
        rdata,
        rresp,
        rvalid,
        rready,
        awaddr,
        awvalid,
        awready,
        wdata,
        wvalid,
        wready,
        bresp,
        bvalid, 
        bready,
        read_en,
        read_data,
        empty,
        write_en,
        write_data,
        full
    );

    // VCD dump file
    initial begin
        $dumpfile("axi4slave_tb.vcd");
        $dumpvars(0, axi4lite_slave_tb);
        
        //Initialize
        clk = 1;
        arestn = 0;
        araddr = 32'h0;
        arvalid = 1'b0;
        rready = 1'b0;
        awaddr = 32'h0;
        awvalid = 1'b0;
        wdata = 32'h0;
        wvalid = 1'b0;
        bready = 1'b0;

        read_data = 32'h0;
        empty = 1'b0;
        full = 1'b0;
 
        #10;
        // write transaction
        arestn = 1;

        #20;
        araddr = 32'h00000000;
        arvalid = 1'b0;
        rready = 1'b0;
        awaddr = 32'hA5A5A5A5;
        awvalid = 1'b1;
        wdata = 32'hB5B5B5B5;
        wvalid = 1'b1;
        bready = 1'b1;

        #20;
        araddr = 32'h00000000;
        arvalid = 1'b0;
        rready = 1'b0;
        awaddr = 32'h00000000;
        wdata = 32'h00000000;
        
        #20;
        araddr = 32'hA5A5A5A5;
        arvalid = 1'b1;
        rready = 1'b1;
        awaddr = 32'h00000000;
        awvalid = 1'b0;
        wdata = 32'h00000000;
        wvalid = 1'b0;
        bready = 1'b0;

        #40;
        
        #10;
        // Perform additional read and write operations as needed
        // End simulation
        $finish;
    end

    // Clock generation
    always begin
        #5 clk = ~clk;
    end

    // axi master control 
    always@(posedge clk)begin
        if(bready && bvalid)
            #2 bready = 1'b0;
        if(awvalid && awready)
            awvalid = 1'b0;
        if(wvalid && wready)
            wvalid = 1'b0;
        if(arvalid && arready)
            arvalid = 1'b0;
        if(rvalid && rready)
            rready = 1'b0;
    end

endmodule

tb/axi4/axi4slave_tb.vcd
$date
	Sun Nov 19 10:56:35 2023
$end
$version
	Icarus Verilog
$end
$timescale
	1ps
$end
$scope module axi4lite_slave_tb $end
$var wire 2 ! bresp [1:0] $end
$var wire 2 " rresp [1:0] $end
$var wire 1 # write_en $end
$var wire 64 $ write_data [63:0] $end
$var wire 1 % wready $end
$var wire 1 & rvalid $end
$var wire 1 ' read_en $end
$var wire 32 ( rdata [31:0] $end
$var wire 1 ) bvalid $end
$var wire 1 * awready $end
$var wire 1 + arready $end
$var reg 32 , araddr [31:0] $end
$var reg 1 - arestn $end
$var reg 1 . arvalid $end
$var reg 32 / awaddr [31:0] $end
$var reg 1 0 awvalid $end
$var reg 1 1 bready $end
$var reg 1 2 clk $end
$var reg 1 3 empty $end
$var reg 1 4 full $end
$var reg 32 5 read_data [31:0] $end
$var reg 1 6 rready $end
$var reg 32 7 wdata [31:0] $end
$var reg 1 8 wvalid $end
$scope module my_slave $end
$var wire 1 2 aclk $end
$var wire 32 9 araddr [31:0] $end
$var wire 1 - arestn $end
$var wire 1 . arvalid $end
$var wire 32 : awaddr [31:0] $end
$var wire 1 0 awvalid $end
$var wire 1 1 bready $end
$var wire 2 ; bresp [1:0] $end
$var wire 1 3 empty $end
$var wire 1 4 full $end
$var wire 32 < rdata [31:0] $end
$var wire 32 = read_data [31:0] $end
$var wire 1 ' read_en $end
$var wire 1 6 rready $end
$var wire 2 > rresp [1:0] $end
$var wire 32 ? wdata [31:0] $end
$var wire 1 % wready $end
$var wire 1 # write_en $end
$var wire 1 8 wvalid $end
$var wire 64 @ write_data [63:0] $end
$var wire 1 A reset $end
$var reg 1 + arready $end
$var reg 1 * awready $end
$var reg 1 ) bvalid $end
$var reg 1 & rvalid $end
$upscope $end
$upscope $end
$enddefinitions $end
#0
$dumpvars
1A
b0 @
b0 ?
b0 >
b0 =
b0 <
b0 ;
b0 :
b0 9
08
b0 7
06
b0 5
04
03
12
01
00
b0 /
0.
0-
b0 ,
0+
0*
0)
b0 (
0'
0&
0%
b0 $
0#
b0 "
b0 !
$end
#5000
02
#10000
12
0A
1-
#15000
02
#20000
12
#25000
02
#30000
1%
1*
12
11
18
b10110101101101011011010110110101 7
b10110101101101011011010110110101 ?
10
b1010010110100101101001011010010110110101101101011011010110110101 $
b1010010110100101101001011010010110110101101101011011010110110101 @
b10100101101001011010010110100101 /
b10100101101001011010010110100101 :
#35000
02
#40000
1#
1)
0%
0*
00
12
#45000
02
#50000
0#
0)
01
12
b0 7
b0 ?
b0 $
b0 @
b0 /
b0 :
#55000
02
#60000
12
#65000
02
#70000
1+
12
08
16
1.
b10100101101001011010010110100101 ,
b10100101101001011010010110100101 9
#75000
02
#80000
1'
1&
0+
0.
12
#85000
02
#90000
0'
0&
06
12
