axi4/axi4lite_slave.v
module axi4lite_slave(
    
    input wire aclk,
    input wire arestn,
    
    // read address channel
    input wire [31:0] araddr,
    input wire arvalid,
    output wire arready,

    // read data channel
    output reg [31:0] rdata,
    output wire [1:0] rresp,
    output reg rvalid,
    input wire rready,

    // write address channel
    input wire [31:0] awaddr,
    input wire awvalid,
    output reg awready,

    // write data channel
    input wire [31:0] wdata,
    input wire wvalid,
    output wire wready,

    // write response
    output wire [1:0] bresp,
    output reg bvalid, 
    input wire bready

);

    // rresp or bresp
    // 0b00 - OKAY
    // 0b01 - EXOKAY
    // 0b10 - SLVERR
    // 0b11 - DECERR



    /* Hanlding Write operation from Master

    - Master Puts data and address and asserts AWVALID, WVALID, BREADY
    - Slave asserts AWREADY and WRREADY when ready to accept. Master deasserts valid and ready on bothe address and data
    - ASsert BVALID 
    - Deassert both in BVALID and BREADY are high

    */



    /* Handling Read operation from Master

    - Read address, ARVALID, RREADY from master.
    - ARREADY by slave
    - ARVALID and ARREADY deasserted 
    - puts requested data on bus and RVALID
    - Since both RREADY and RVALID , deasserted

    */

    assign	reset = !arestn;
    assign	wready = awready;

    assign rresp = 2'b00;
    assign bresp = 2'b00;
    

    assign arready = (arvalid && arready);


    initial	awready = 1'b0;
    initial	bvalid = 1'b0;
    initial rvalid = 1'b0;

    always @ (posedge aclk)begin

        if(reset)
        begin
            #2 bvalid <= 1'b0;
            #2 rvalid <=1'b0; 
            // Clear FIFO
        end
        else if(wready)begin
            // write to FIFO        
            #2 bvalid <= 1'b1;
        end
        else if(bready && bvalid)
            #2 bvalid <= 1'b0

    end
    
    always @(posedge aclk)begin
        if(reset)
            awready <= 1'b0;
        else
            awready <= !awready && (awvalid && wvalid) && (!bvalid && bready);

    end
    
    always @(*)begin
        arready = !rvalid;
    end
    
    always @(posedge aclk)begin
        if(!rvalid || rready)
            #2 rdata <= //fifo output ;
        else if (rready)
            #2 rvalid = 1'b1;

 
    end




endmodule

tb/axi4/axi4lite_slave_tb.v
`timescale 1ns / 1ps
`include "../../axi4/axi4lite_slave.v"

/*

timing checks on 
https://www.realdigital.org/doc/a9fee931f7a172423e1ba73f66ca4081


*/
module axi4lite_slave_tb();
    
    reg clk;
    reg arestn;
    
    // read address channel
    reg [31:0] araddr;
    reg arvalid;
    wire arready;

    // read data channel
    wire [31:0] rdata;
    wire [1:0] rresp;
    wire rvalid;
    reg rready;

    // write address channel
    reg [31:0] awaddr;
    reg awvalid;
    wire awready;

    // write data channel
    reg [31:0] wdata;
    reg wvalid;
    wire wready;

    // write response
    wire [1:0] bresp;
    wire bvalid; 
    reg bready;

    // Instantiate the FIFO module
    axi4lite_slave my_slave (
        clk,
        arestn,
        araddr,
        arvalid,
        arready,
        rdata,
        rresp,
        rvalid,
        rready,
        awaddr,
        awvalid,
        awready,
        wdata,
        wvalid,
        wready,
        bresp,
        bvalid, 
        bready
    );

    // VCD dump file
    initial begin
        $dumpfile("axi4slave_tb.vcd");
        $dumpvars(0, axi4lite_slave_tb);
        
        //Initialize
        clk = 0;
        arestn = 0;
        araddr = 32'h0;
        arvalid = 1'b0;
        rready = 1'b0;
        awaddr = 32'h0;
        awvalid = 1'b0;
        wdata = 32'h0;
        wvalid = 1'b0;
        bready = 1'b0;
 
        #10;
        // write transaction
        arestn = 1;

        #20;
        araddr = 32'h00000000;
        arvalid = 1'b0;
        rready = 1'b0;
        awaddr = 32'hA5A5A5A5;
        awvalid = 1'b1;
        wdata = 32'hB5B5B5B5;
        wvalid = 1'b1;
        bready = 1'b1;

        #20;
        araddr = 32'h00000000;
        arvalid = 1'b0;
        rready = 1'b0;
        awaddr = 32'h00000000;
        wdata = 32'h00000000;

        #40;
        araddr = 32'hA5A5A5A5;
        arvalid = 1'b1;
        rready = 1'b1;
        awaddr = 32'h0;
        awvalid = 1'b0;
        wdata = 32'h0;
        wvalid = 1'b0;
        bready = 1'b0;
        
        #40;
        
        #10;
        // Perform additional read and write operations as needed
        // End simulation
        $finish;
    end

    // Clock generation
    always begin
        #10 clk = ~clk;
    end

    // axi master control 
    always@(posedge clk)begin
        if(bready && bvalid)
            bready = 1'b0;
        if(awvalid && awready)
            awvalid = 1'b0;
        if(wvalid && wready)
            wvalid = 1'b0;
        if(arvalid && arready)
            arvalid = 1'b0;
        if(rvalid && rready)
            rready = 1'b0;
    end

endmodule

tb/axi4/axi4slave_tb.vcd
$date
	Tue Nov 14 12:40:37 2023
$end
$version
	Icarus Verilog
$end
$timescale
	1ps
$end
$scope module axi4lite_slave_tb $end
$var wire 2 ! bresp [1:0] $end
$var wire 2 " rresp [1:0] $end
$var wire 1 # wready $end
$var wire 1 $ rvalid $end
$var wire 32 % rdata [31:0] $end
$var wire 1 & bvalid $end
$var wire 1 ' awready $end
$var wire 1 ( arready $end
$var reg 32 ) araddr [31:0] $end
$var reg 1 * arestn $end
$var reg 1 + arvalid $end
$var reg 32 , awaddr [31:0] $end
$var reg 1 - awvalid $end
$var reg 1 . bready $end
$var reg 1 / clk $end
$var reg 1 0 rready $end
$var reg 32 1 wdata [31:0] $end
$var reg 1 2 wvalid $end
$scope module my_slave $end
$var wire 1 / aclk $end
$var wire 32 3 araddr [31:0] $end
$var wire 1 * arestn $end
$var wire 1 + arvalid $end
$var wire 32 4 awaddr [31:0] $end
$var wire 1 - awvalid $end
$var wire 1 . bready $end
$var wire 2 5 bresp [1:0] $end
$var wire 1 0 rready $end
$var wire 2 6 rresp [1:0] $end
$var wire 32 7 wdata [31:0] $end
$var wire 1 # wready $end
$var wire 1 2 wvalid $end
$var wire 1 8 reset $end
$var reg 1 ( arready $end
$var reg 1 ' awready $end
$var reg 1 & bvalid $end
$var reg 32 9 rdata [31:0] $end
$var reg 1 $ rvalid $end
$upscope $end
$upscope $end
$enddefinitions $end
#0
$dumpvars
bx 9
18
b0 7
b0 6
b0 5
b0 4
b0 3
02
b0 1
00
0/
0.
0-
b0 ,
0+
0*
b0 )
0(
0'
0&
bx %
0$
0#
b0 "
b0 !
$end
#10000
1/
08
1*
#20000
0/
#30000
1#
1'
1/
1.
12
b10110101101101011011010110110101 1
b10110101101101011011010110110101 7
1-
b10100101101001011010010110100101 ,
b10100101101001011010010110100101 4
#40000
0/
#50000
0#
0'
02
0-
1/
b0 1
b0 7
b0 ,
b0 4
#52000
1&
#60000
0/
#70000
0.
1/
#72000
0&
#80000
0/
#90000
1(
1/
10
1+
b10100101101001011010010110100101 )
b10100101101001011010010110100101 3
#100000
0/
#110000
1$
b10100101101001011010010110100101 %
b10100101101001011010010110100101 9
0(
0+
1/
#120000
0/
#130000
00
1/
