fifo/async_fifo_util/wptr_full.v
module wptr_full (
    output reg wfull,
    output [ADDRSIZE-1:0] waddr,
    output reg [ADDRSIZE:0] wptr,
    input [ADDRSIZE:0] wq2_rptr,
    input   winc, wclk, wrst_n
);

    parameter ADDRSIZE = 5;

    reg [ADDRSIZE:0] wbin;
    wire [ADDRSIZE:0] wgraynext, wbinnext;

    // GRAYSTYLE2 pointer
    always @(posedge wclk or negedge wrst_n)begin
        if (!wrst_n) 
            {wbin, wptr} <= 0;
        else
            {wbin, wptr} <= {wbinnext, wgraynext};
    end
    

    // Memory write-address pointer (okay to use binary to address memory)
    assign waddr = wbin[ADDRSIZE-1:0];
    assign wbinnext = wbin + (winc & ~wfull);
    assign wgraynext = (wbinnext>>1) ^ wbinnext;

    //------------------------------------------------------------------
    // Simplified version of the three necessary full-tests:
    //assign wfull_val=((wgnext[5]!=wq2_rptr[5] ) &&
    //(wgnext[ADDRSIZE-1] !=wq2_rptr[ADDRSIZE-1]) &&
    //(wgnext[ADDRSIZE-2:0]==wq2_rptr[ADDRSIZE-2:0]));
    //------------------------------------------------------------------
    //
    assign wfull_val = (wgraynext=={~wq2_rptr[ADDRSIZE:ADDRSIZE-1],wq2_rptr[ADDRSIZE-2:0]});

    always @(posedge wclk or negedge wrst_n)begin
        if (!wrst_n) 
            wfull <= 1'b0;
        else
            wfull <= wfull_val;
    end

endmodule

fifo/aync_fifo_util/rptr_empty.v
module rptr_empty (
    output reg rempty,
    output [4:0] raddr,
    output reg [5:0] rptr,
    input [5:0] rq2_wptr,
    input rinc, rclk, rrst_n
);
    reg [5:0] rbin;
    wire [5:0] rgraynext, rbinnext;

    //-------------------
    // GRAYSTYLE2 pointer
    //-------------------
    always @(posedge rclk or negedge rrst_n)begin
        if (!rrst_n) 
            {rbin, rptr} <= 0;
        else
            {rbin, rptr} <= {rbinnext, rgraynext};
    end

    // Memory read-address pointer (okay to use binary to address memory)
    assign raddr= rbin[4:0];
    assign rbinnext = rbin + (rinc & ~rempty);
    assign rgraynext = (rbinnext>>1) ^ rbinnext;

    //---------------------------------------------------------------
    // FIFO empty when the next rptr == synchronized wptr or on reset
    //---------------------------------------------------------------
    assign rempty_val = (rgraynext == rq2_wptr);

    always @(posedge rclk or negedge rrst_n)begin
        if (!rrst_n) 
            rempty <= 1'b1;
        else
            rempty <= rempty_val;
    end
endmodule

fifo/aync_fifo_util/fifo_mem.v
module fifomem (
    output [DEPTH-1:0] rdata,
    input [DEPTH-1:0] wdata,
    input [MSB_SLOT:0] waddr, raddr,
    input wclken, wfull, wclk
);

    parameter DEPTH = 32;
    parameter LENGTH = 32;
    parameter MSB_SLOT = 4;

    // RTL Verilog memory model
    // localparam DEPTH = 1<<5;
    //
    reg [LENGTH-1:0] mem [0:DEPTH-1];

    assign rdata = mem[raddr];

    always @(posedge wclk)
        if (wclken && !wfull) mem[waddr] <= wdata;
endmodule

fifo/async_fifo_util/sync_w2r.v
module sync_w2r(
    output reg [ADDRSIZE:0] rq2_wptr,
    input [ADDRSIZE:0] wptr,
    input rclk, rrst_n
);
    parameter ADDRSIZE = 5;

    reg [ADDRSIZE:0] rq1_wptr;

    always @(posedge rclk or negedge rrst_n)begin
        if (!rrst_n) 
            {rq2_wptr,rq1_wptr} <= 0;
        else
            {rq2_wptr,rq1_wptr} <= {rq1_wptr,wptr};
    end
endmodule

fifo/async_fifo_util/sync_r2w.v
module sync_r2w(
    output reg [ADDRSIZE:0] wq2_rptr,
    input [ADDRSIZE:0] rptr,
    input wclk, wrst_n
);

    parameter ADDRSIZE = 5;

    reg [ADDRSIZE:0] wq1_rptr;

    always @(posedge wclk or negedge wrst_n)begin
        if (!wrst_n)
            {wq2_rptr,wq1_rptr} <= 0;

        else
            {wq2_rptr,wq1_rptr} <= {wq1_rptr,rptr};
    end
endmodule

fifo/async_fifo.v
/*

File : async_fifo.v
Description: Top module file for the async fifo 

Ref: Cummings

32 bit x 32 slots

Have to test this implementation before integration

*/

`include "../../fifo/async_fifo_util/fifo_mem.v"
`include "../../fifo/async_fifo_util/sync_r2w.v"
`include "../../fifo/async_fifo_util/sync_w2r.v"
`include "../../fifo/async_fifo_util/rptr_empty.v"
`include "../../fifo/async_fifo_util/wptr_full.v"


module async_fifo(
    output [DSIZE-1:0] rdata, 
    output wfull, 
    output rempty, 
    input [DSIZE-1:0] wdata, 
    input winc, wclk, wrst_n, 
    input rinc, rclk, rrst_n
); 
    
    parameter DSIZE = 32;
    parameter ADDRSIZE = 5;

    wire [ADDRSIZE-1:0] waddr, raddr; 
    // extra bit used to check for full/empty
    wire [ADDRSIZE:0] wptr, rptr, wq2_rptr, rq2_wptr; 

    sync_r2w #(.ADDRSIZE(ADDRSIZE)) sync_r2w (
        .wq2_rptr(wq2_rptr), 
        .rptr(rptr), 
        .wclk(wclk), 
        .wrst_n(wrst_n)
    ); 
        
    sync_w2r #(.ADDRSIZE(ADDRSIZE))sync_w2r (
        .rq2_wptr(rq2_wptr), 
        .wptr(wptr), 
        .rclk(rclk), 
        .rrst_n(rrst_n)
    ); 
        
    fifomem #(.ADDRSIZE(ADDRSIZE), .DSIZE(DSIZE)) fifomem (
        .rdata(rdata), 
        .wdata(wdata), 
        .waddr(waddr), 
        .raddr(raddr), 
        .wclken(winc), 
        .wfull(wfull), 
        .wclk(wclk)
    ); 
        
    rptr_empty #(.ADDRSIZE(ADDRSIZE)) rptr_empty (
        .rempty(rempty), 
        .raddr(raddr), 
        .rptr(rptr), 
        .rq2_wptr(rq2_wptr), 
        .rinc(rinc), 
        .rclk(rclk), 
        .rrst_n(rrst_n)
    ); 
    
    wptr_full #(.ADDRSIZE(ADDRSIZE))wptr_full (
        .wfull(wfull), 
        .waddr(waddr), 
        .wptr(wptr), 
        .wq2_rptr(wq2_rptr), 
        .winc(winc), 
        .wclk(wclk), 
        .wrst_n(wrst_n)
    ); 

endmodule

tb/fifo/async_fifo_tb.v
`timescale 1ns / 1ps
`include "../../fifo/async_fifo.v"

module async_fifo_tb();

    localparam  DSIZE = 32;
    localparam  ADDRSIZE = 5;

    // Define testbench signals
    wire [DSIZE-1:0] rdata;
    wire wfull;
    wire rempty; 

    reg [DSIZE-1:0] wdata; 
    reg winc, wclk, wrst_n; 
    reg rinc, rclk, rrst_n;


    // Instantiate the FIFO module
    async_fifo #(.ADDRSIZE(ADDRSIZE), .DSIZE(DSIZE)) my_fifo(
        .rdata(rdata),
        .wfull(wfull),
        .rempty(rempty), 
        .wdata(wdata), 
        .winc(winc),
        .wclk(wclk), 
        .wrst_n(wrst_n), 
        .rinc(rinc), 
        .rclk(rclk), 
        .rrst_n(rrst_n)
    ); 
    


    // VCD dump file
    initial begin
        $dumpfile("async_fifo_tb.vcd");
        $dumpvars(0, async_fifo_tb);

        // Initialize signals
        wclk = 1;
        rclk = 1;
        wrst_n = 0;
        rrst_n = 0;

        winc = 0;
        rinc = 0;
        wdata = 32'h0;

        #20;
        // Release reset
        wrst_n = 1;
        rrst_n = 1;

        winc = 1;
        rinc = 0;
        wdata = 32'h0000BBBB;

        // Have to deassert winc before next clock posedge for correct
        // operation 

        #5;
        winc = 0;
        
        #20;

        winc = 1;
        rinc = 0;
        wdata = 32'h00010001;

        #20;

        winc = 1;
        rinc = 0;
        wdata = 32'h00010001;

        #20;
        winc = 0;
        rinc = 1;

        #20;
        winc = 1;
        rinc = 1;
        wdata = 32'h0100CCCC;

        #20;
        winc = 0;
        rinc = 1;

        #20;
        winc = 0;
        rinc = 1;

        #20;
        winc = 0;
        rinc = 0;

        #40;
        // Perform additional read and write operations as needed
        // End simulation
        $finish;
    end

    // Clock generation
    always begin
        #5 wclk = ~wclk;
    end
    always begin
        #10 rclk = ~rclk;
    end

endmodule

tb/ni/async_fifo_tb.vcd
$date
	Tue Jan 30 08:56:22 2024
$end
$version
	Icarus Verilog
$end
$timescale
	1ps
$end
$scope module async_fifo_tb $end
$var wire 1 ! wfull $end
$var wire 1 " rempty $end
$var wire 32 # rdata [31:0] $end
$var reg 1 $ rclk $end
$var reg 1 % rinc $end
$var reg 1 & rrst_n $end
$var reg 1 ' wclk $end
$var reg 32 ( wdata [31:0] $end
$var reg 1 ) winc $end
$var reg 1 * wrst_n $end
$scope module my_fifo $end
$var wire 1 $ rclk $end
$var wire 1 % rinc $end
$var wire 1 & rrst_n $end
$var wire 1 ' wclk $end
$var wire 32 + wdata [31:0] $end
$var wire 1 ) winc $end
$var wire 1 * wrst_n $end
$var wire 6 , wq2_rptr [5:0] $end
$var wire 6 - wptr [5:0] $end
$var wire 1 ! wfull $end
$var wire 5 . waddr [4:0] $end
$var wire 6 / rq2_wptr [5:0] $end
$var wire 6 0 rptr [5:0] $end
$var wire 1 " rempty $end
$var wire 32 1 rdata [31:0] $end
$var wire 5 2 raddr [4:0] $end
$scope module fifomem $end
$var wire 32 3 rdata [31:0] $end
$var wire 1 ' wclk $end
$var wire 1 ) wclken $end
$var wire 32 4 wdata [31:0] $end
$var wire 1 ! wfull $end
$var wire 5 5 waddr [4:0] $end
$var wire 5 6 raddr [4:0] $end
$upscope $end
$scope module rptr_empty $end
$var wire 1 $ rclk $end
$var wire 6 7 rgraynext [5:0] $end
$var wire 1 % rinc $end
$var wire 1 & rrst_n $end
$var wire 6 8 rq2_wptr [5:0] $end
$var wire 1 9 rempty_val $end
$var wire 6 : rbinnext [5:0] $end
$var wire 5 ; raddr [4:0] $end
$var reg 6 < rbin [5:0] $end
$var reg 1 " rempty $end
$var reg 6 = rptr [5:0] $end
$upscope $end
$scope module sync_r2w $end
$var wire 6 > rptr [5:0] $end
$var wire 1 ' wclk $end
$var wire 1 * wrst_n $end
$var reg 6 ? wq1_rptr [5:0] $end
$var reg 6 @ wq2_rptr [5:0] $end
$upscope $end
$scope module sync_w2r $end
$var wire 1 $ rclk $end
$var wire 1 & rrst_n $end
$var wire 6 A wptr [5:0] $end
$var reg 6 B rq1_wptr [5:0] $end
$var reg 6 C rq2_wptr [5:0] $end
$upscope $end
$scope module wptr_full $end
$var wire 1 ' wclk $end
$var wire 6 D wgraynext [5:0] $end
$var wire 1 ) winc $end
$var wire 6 E wq2_rptr [5:0] $end
$var wire 1 * wrst_n $end
$var wire 1 F wfull_val $end
$var wire 6 G wbinnext [5:0] $end
$var wire 5 H waddr [4:0] $end
$var reg 6 I wbin [5:0] $end
$var reg 1 ! wfull $end
$var reg 6 J wptr [5:0] $end
$upscope $end
$upscope $end
$upscope $end
$enddefinitions $end
#0
$dumpvars
b0 J
b0 I
b0 H
b0 G
0F
b0 E
b0 D
b0 C
b0 B
b0 A
b0 @
b0 ?
b0 >
b0 =
b0 <
b0 ;
b0 :
19
b0 8
b0 7
b0 6
b0 5
b0 4
bx 3
b0 2
bx 1
b0 0
b0 /
b0 .
b0 -
b0 ,
b0 +
0*
0)
b0 (
1'
0&
0%
1$
bx #
1"
0!
$end
#5000
0'
#10000
1'
0$
#15000
0'
#20000
b1 .
b1 5
b1 H
b1011101110111011 #
b1011101110111011 1
b1011101110111011 3
b1 I
b11 D
b10 G
1'
1$
b1011101110111011 (
b1011101110111011 +
b1011101110111011 4
1)
1&
1*
#25000
b1 D
b1 G
0'
0)
#30000
b1 -
b1 A
b1 J
1'
0$
#35000
0'
#40000
b1 B
1'
1$
#45000
b11 D
b10 G
0'
b10000000000000001 (
b10000000000000001 +
b10000000000000001 4
1)
#50000
b10 .
b10 5
b10 H
b10 D
b11 G
b10 I
b11 -
b11 A
b11 J
1'
0$
#55000
0'
#60000
b11 .
b11 5
b11 H
b110 D
b100 G
b11 I
b10 -
b10 A
b10 J
09
b1 /
b1 8
b1 C
b11 B
1'
1$
#65000
0'
#70000
b100 .
b100 5
b100 H
b111 D
b101 G
b100 I
b110 -
b110 A
b110 J
1'
0$
#75000
0'
#80000
b101 .
b101 5
b101 H
b101 D
b110 G
b101 I
b111 -
b111 A
b111 J
b11 /
b11 8
b11 C
b110 B
0"
1'
1$
#85000
b1 7
b111 D
b1 :
b101 G
0'
1%
0)
#90000
1'
0$
#95000
0'
#100000
b10000000000000001 #
b10000000000000001 1
b10000000000000001 3
b1 2
b1 6
b1 ;
b11 7
b10 :
b1 <
b1 0
b1 =
b1 >
b110 /
b110 8
b110 C
b111 B
1'
1$
#105000
b101 D
b110 G
0'
b1000000001100110011001100 (
b1000000001100110011001100 +
b1000000001100110011001100 4
1)
#110000
b110 .
b110 5
b110 H
b100 D
b111 G
b110 I
b101 -
b101 A
b101 J
b1 ?
1'
0$
#115000
0'
#120000
b111 .
b111 5
b111 H
b1100 D
b10 2
b10 6
b10 ;
b10 7
b1 ,
b1 @
b1 E
b1000 G
b111 I
b100 -
b100 A
b100 J
b111 /
b111 8
b111 C
b101 B
b11 :
b10 <
b11 0
b11 =
b11 >
1'
1$
#125000
b100 D
b111 G
0'
0)
#130000
b11 ?
1'
0$
#135000
0'
#140000
b11 2
b11 6
b11 ;
09
b110 7
b11 ,
b11 @
b11 E
b100 :
b11 <
b10 0
b10 =
b10 >
b101 /
b101 8
b101 C
b100 B
1'
1$
#145000
0'
#150000
b10 ?
1'
0$
#155000
0'
#160000
b100 2
b100 6
b100 ;
b111 7
b10 ,
b10 @
b10 E
b100 /
b100 8
b100 C
b101 :
b100 <
b110 0
b110 =
b110 >
1'
1$
#165000
b110 7
b100 :
0'
0%
#170000
b110 ?
1'
0$
#175000
0'
#180000
b110 ,
b110 @
b110 E
1'
1$
