fifo/gp_fifo.v
/*

File: gp_fifo.v
Descripton: Simple FIFO module

General purpose FIFO to handle the read and write buffer.
The whole FIFO runs on the same clock domain (ie. not the async version )

The below can be changed with the use of parameters
32 slots of 32 bits

Tested for same time reads and writes

*/
//  #(parameter LENGTH = 32 , MSB_SLOT = 4, DEPTH = 32)
module gp_fifo(
    input clk,
    input reset,
    input write_en,
    input read_en,
    input [DEPTH-1:0] data_in,
    output reg [DEPTH-1:0] data_out,
    output reg error,
    output reg full,
    output reg empty,
    output reg [MSB_SLOT:0] ocup
);


    parameter LENGTH = 32;
    // this is one less than MSB thie is for the length of fifo (32bit -> 5 )
    // `define MSB_SLOT 4
    parameter MSB_SLOT = 4;
    parameter DEPTH =  32;



    reg [DEPTH-1:0] fifo_ff [LENGTH-1:0]; 
    reg [MSB_SLOT:0] write_ptr_ff,read_ptr_ff, next_write_ptr, next_read_ptr,fifo_ocup;

    always@*begin
        next_read_ptr = read_ptr_ff;
        next_write_ptr = write_ptr_ff;

        empty = (write_ptr_ff == read_ptr_ff);
        full = (write_ptr_ff[MSB_SLOT-1:0] == read_ptr_ff[MSB_SLOT-1:0] ) 
            && (write_ptr_ff[MSB_SLOT]!= read_ptr_ff[MSB_SLOT]);
                
        data_out = empty ? 0 : fifo_ff[read_ptr_ff[MSB_SLOT-1:0]];
        
        if (write_en && ~full)
            next_write_ptr = write_ptr_ff + 1'b1;

        if (read_en && ~empty)
            next_read_ptr = read_ptr_ff + 1'b1;

        error = (write_en && full) || (read_en && empty);
        fifo_ocup = write_ptr_ff - read_ptr_ff;
        ocup = fifo_ocup;
    end

    integer i;
    always@(posedge clk or posedge reset)begin
        if(reset) begin
            write_ptr_ff <= 1'b0;
            read_ptr_ff <= 1'b0;
            for (i = 0; i < 32; i = i + 1)
            begin
                fifo_ff[i] <= 0;       // Write zero to all registers
            end
        end
        else begin
            write_ptr_ff <= next_write_ptr;
            read_ptr_ff <= next_read_ptr;
            if (write_en && ~full)
                fifo_ff[write_ptr_ff[MSB_SLOT-1:0]] <= data_in;
        end
    end
endmodule

tb/ni/gp_fifo_tb.v
`timescale 1ns / 1ps
`include "../../fifo/gp_fifo.v"

module gp_fifo_tb();

    localparam  LENGTH = 32;
    localparam  DEPTH = 32;
    localparam  MSB_SLOT = 4;

    // Define testbench signals
    reg clk;
    reg reset;
    reg write_en;
    reg read_en;
    reg [DEPTH-1:0] data_in;
    wire [DEPTH-1:0] data_out;
    wire error;
    wire full;
    wire empty;
    wire [MSB_SLOT:0] ocup;

    // Instantiate the FIFO module
    gp_fifo #(.LENGTH(LENGTH) , .MSB_SLOT(MSB_SLOT), .DEPTH(DEPTH)) my_fifo(
        .clk(clk),
        .reset(reset),
        .write_en(write_en),
        .read_en(read_en),
        .data_in(data_in),
        .data_out(data_out),
        .error(error),
        .full(full),
        .empty(empty),
        .ocup(ocup)
    );

    // VCD dump file
    initial begin
        $dumpfile("gp_fifo_tb.vcd");
        $dumpvars(0, gp_fifo_tb);

        // Initialize signals
        clk = 1;
        reset = 1;
        write_en = 1'b0;
        read_en = 1'b0;
        data_in = 32'h0;

        #10;
        // Release reset
        reset = 1'b0;
        // Write data to the FIFO
        write_en = 1;
        data_in = 32'h0101A5A5;// Example data
        
        #10;
        // Release reset
        reset = 1'b0;
        // Write data to the FIFO
        write_en = 1;
        data_in = 32'h0000BBBB; // Example data

        #10;
        // Write data to the FIFO
        write_en = 1;
        data_in = 32'h00010001; // Example data


        #10;
        write_en = 0;
        // Read data from the FIFO
        read_en = 1;


        #10;
        read_en = 1;
        write_en = 1;
        data_in = 64'h0100CCCC; // Example data

        #10;
        write_en = 0;
        // Read data from the FIFO
        read_en = 1;

        #10;
        write_en = 0;
        // Read data from the FIFO
        read_en = 1;

        #10;
        read_en = 0;
        write_en = 0;
        #40;
        // Perform additional read and write operations as needed
        // End simulation
        $finish;
    end

    // Clock generation
    always begin
        #5 clk = ~clk;
    end

endmodule

tb/ni/gp_fifo_tb.vcd
$date
	Wed Nov 22 10:05:18 2023
$end
$version
	Icarus Verilog
$end
$timescale
	1ps
$end
$scope module gp_fifo_tb $end
$var wire 5 ! ocup [4:0] $end
$var wire 1 " full $end
$var wire 1 # error $end
$var wire 1 $ empty $end
$var wire 32 % data_out [31:0] $end
$var reg 1 & clk $end
$var reg 32 ' data_in [31:0] $end
$var reg 1 ( read_en $end
$var reg 1 ) reset $end
$var reg 1 * write_en $end
$scope module my_fifo $end
$var wire 1 & clk $end
$var wire 32 + data_in [31:0] $end
$var wire 1 ( read_en $end
$var wire 1 ) reset $end
$var wire 1 * write_en $end
$var reg 32 , data_out [31:0] $end
$var reg 1 $ empty $end
$var reg 1 # error $end
$var reg 5 - fifo_ocup [4:0] $end
$var reg 1 " full $end
$var reg 5 . next_read_ptr [4:0] $end
$var reg 5 / next_write_ptr [4:0] $end
$var reg 5 0 ocup [4:0] $end
$var reg 5 1 read_ptr_ff [4:0] $end
$var reg 5 2 write_ptr_ff [4:0] $end
$var integer 32 3 i [31:0] $end
$upscope $end
$upscope $end
$enddefinitions $end
#0
$dumpvars
b100000 3
b0 2
b0 1
b0 0
b0 /
b0 .
b0 -
b0 ,
b0 +
0*
1)
0(
b0 '
1&
b0 %
1$
0#
0"
b0 !
$end
#5000
0&
#10000
b1 !
b1 0
b1 -
b1000000011010010110100101 %
b1000000011010010110100101 ,
0$
b1 2
b10 /
1&
b1000000011010010110100101 '
b1000000011010010110100101 +
1*
0)
#15000
0&
#20000
b10 !
b10 0
b10 -
b11 /
b10 2
1&
b1011101110111011 '
b1011101110111011 +
#25000
0&
#30000
b11 !
b11 0
b11 -
b100 /
b11 2
1&
b10000000000000001 '
b10000000000000001 +
#35000
0&
#40000
b10 !
b10 0
b10 -
b1011101110111011 %
b1011101110111011 ,
b1 1
b10 .
b11 /
1&
1(
0*
#45000
0&
#50000
b10000000000000001 %
b10000000000000001 ,
b10 1
b100 2
b101 /
b11 .
1&
b1000000001100110011001100 '
b1000000001100110011001100 +
1*
#55000
0&
#60000
b1 !
b1 0
b1 -
b1000000001100110011001100 %
b1000000001100110011001100 ,
b11 1
b100 /
b100 .
1&
0*
#65000
0&
#70000
b0 !
b0 0
b0 -
1#
b0 %
b0 ,
1$
b100 1
1&
#75000
0&
#80000
0#
1&
0(
