fifo/gp_fifo.v
/*

File: gp_fifo.v
Descripton: Simple FIFO module

General purpose FIFO to handle the read and write buffer.
The whole FIFO runs on the same clock domain (ie. not the async version )

32 slots of 64 bits

*/

module gp_fifo(
    input clk,
    input reset,
    input write_en,
    input read_en,
    input [63:0] data_in,
    output reg [63:0] data_out,
    output reg error,
    output reg full,
    output reg empty,
    output reg [4:0] ocup
);

    // this is one less than MSB (32bit -> 5 )
    `define MSB_SLOT 5

    reg [63:0] fifo_ff [31:0]; 
    reg [`MSB_SLOT:0] write_ptr_ff,read_ptr_ff, next_write_ptr, next_read_ptr,fifo_ocup;

    always@*begin
        next_read_ptr = read_ptr_ff;
        next_write_ptr = write_ptr_ff;

        empty = (write_ptr_ff == read_ptr_ff);
        full = (write_ptr_ff[`MSB_SLOT-1:0] == read_ptr_ff[`MSB_SLOT-1:0] )  && (write_ptr_ff[`MSB_SLOT]!= read_ptr_ff[`MSB_SLOT]);
                
        data_out = empty ? 0 : fifo_ff[read_ptr_ff[`MSB_SLOT-1:0]];
        
        if (write_en && ~full)
            next_write_ptr = write_ptr_ff + 1'b1;

        if (read_en && ~empty)
            next_read_ptr = read_ptr_ff + 1'b1;

        error = (write_en && full) || (read_en && empty);
        fifo_ocup = write_ptr_ff - read_ptr_ff;
        ocup = fifo_ocup;
    end

    integer i;
    always@(posedge clk or posedge reset)begin
        if(reset) begin
            write_ptr_ff <= 1'b0;
            read_ptr_ff <= 1'b0;
            for (i = 0; i < 32; i = i + 1)
            begin
                fifo_ff[i] <= 0;       // Write zero to all registers
            end
        end
        else begin
            write_ptr_ff <= next_write_ptr;
            read_ptr_ff <= next_read_ptr;
            if (write_en && ~full)
                fifo_ff[write_ptr_ff[`MSB_SLOT-1:0]] <= data_in;
        end
    end
endmodule

tb/ni/gp_fifo_tb.v
`timescale 1ns / 1ps
`include "../../fifo/gp_fifo.v"

module gp_fifo_tb();

    // Define testbench signals
    reg clk;
    reg reset;
    reg write_en;
    reg read_en;
    reg [63:0] data_in;
    wire [63:0] data_out;
    wire error;
    wire full;
    wire empty;
    wire [4:0] ocup;

    // Instantiate the FIFO module
    gp_fifo my_fifo (
        .clk(clk),
        .reset(reset),
        .write_en(write_en),
        .read_en(read_en),
        .data_in(data_in),
        .data_out(data_out),
        .error(error),
        .full(full),
        .empty(empty),
        .ocup(ocup)
    );

    // VCD dump file
    initial begin
        $dumpfile("gp_fifo_tb.vcd");
        $dumpvars(0, gp_fifo_tb);

        // Initialize signals
        clk = 1;
        reset = 1;
        write_en = 1'b0;
        read_en = 1'b0;
        data_in = 64'h0;




        #10;
        // Release reset
        reset = 1'b0;
        // Write data to the FIFO
        write_en = 1;
        data_in = 64'hA5A5A5A5A5A5A5A5; // Example data
        
        #1
        write_en = 0;

        #10;
        // Release reset
        reset = 1'b0;
        // Write data to the FIFO
        write_en = 0;
        data_in = 64'hA5A5A5A5A5A5A1A5; // Example data

        #10;
        // Release reset
        reset = 1'b0;
        // Write data to the FIFO
        write_en = 0;
        data_in = 64'hA5A5A5A5A5A5A4A5; // Example data

        #10;
        // Release reset
        reset = 1'b0;
        // Write data to the FIFO
        write_en = 1;
        data_in = 64'h35A5A5A5A5A5A5A5; // Example data

        #10;
        write_en = 0;
        // Read data from the FIFO
        read_en = 1;

        #10;
        // Perform additional read and write operations as needed
        // End simulation
        $finish;
    end

    // Clock generation
    always begin
        #5 clk = ~clk;
    end

endmodule

tb/ni/gp_fifo_tb.vcd
$date
	Fri Nov 17 10:09:43 2023
$end
$version
	Icarus Verilog
$end
$timescale
	1ps
$end
$scope module gp_fifo_tb $end
$var wire 5 ! ocup [4:0] $end
$var wire 1 " full $end
$var wire 1 # error $end
$var wire 1 $ empty $end
$var wire 64 % data_out [63:0] $end
$var reg 1 & clk $end
$var reg 64 ' data_in [63:0] $end
$var reg 1 ( read_en $end
$var reg 1 ) reset $end
$var reg 1 * write_en $end
$scope module my_fifo $end
$var wire 1 & clk $end
$var wire 64 + data_in [63:0] $end
$var wire 1 ( read_en $end
$var wire 1 ) reset $end
$var wire 1 * write_en $end
$var reg 64 , data_out [63:0] $end
$var reg 1 $ empty $end
$var reg 1 # error $end
$var reg 6 - fifo_ocup [5:0] $end
$var reg 1 " full $end
$var reg 6 . next_read_ptr [5:0] $end
$var reg 6 / next_write_ptr [5:0] $end
$var reg 5 0 ocup [4:0] $end
$var reg 6 1 read_ptr_ff [5:0] $end
$var reg 6 2 write_ptr_ff [5:0] $end
$var integer 32 3 i [31:0] $end
$upscope $end
$upscope $end
$enddefinitions $end
#0
$dumpvars
b100000 3
b0 2
b0 1
b0 0
b0 /
b0 .
b0 -
b0 ,
b0 +
0*
1)
0(
b0 '
1&
b0 %
1$
0#
0"
b0 !
$end
#5000
0&
#10000
b1 !
b1 0
b1 -
b1010010110100101101001011010010110100101101001011010010110100101 %
b1010010110100101101001011010010110100101101001011010010110100101 ,
0$
b1 2
b10 /
1&
b1010010110100101101001011010010110100101101001011010010110100101 '
b1010010110100101101001011010010110100101101001011010010110100101 +
1*
0)
#11000
b1 /
0*
#15000
0&
#20000
1&
#21000
b1010010110100101101001011010010110100101101001011010000110100101 '
b1010010110100101101001011010010110100101101001011010000110100101 +
#25000
0&
#30000
1&
#31000
b1010010110100101101001011010010110100101101001011010010010100101 '
b1010010110100101101001011010010110100101101001011010010010100101 +
#35000
0&
#40000
1&
#41000
b10 /
b11010110100101101001011010010110100101101001011010010110100101 '
b11010110100101101001011010010110100101101001011010010110100101 +
1*
#45000
0&
#50000
b10 !
b10 0
b10 -
b11 /
b10 2
1&
#51000
b1 .
b10 /
1(
0*
#55000
0&
#60000
b1 !
b1 0
b1 -
b10 .
b11010110100101101001011010010110100101101001011010010110100101 %
b11010110100101101001011010010110100101101001011010010110100101 ,
b1 1
1&
