fifo/gp_fifo.v
/*

File: gp_fifo.v
Descripton: Simple FIFO module

General purpose FIFO to handle the read and write buffer.
The whole FIFO runs on the same clock domain (ie. not the async version )

Tested for same time reads and writes

*/
module gp_fifo(
    input clk,
    input reset,
    input write_en,
    input read_en,
    input [DEPTH-1:0] data_in,
    output reg [DEPTH-1:0] data_out,
    output reg error,
    output reg full,
    output reg empty,
    output reg [MSB_SLOT:0] ocup
);


    parameter MSB_SLOT = 5;
    parameter ADDRSIZE = 5;
    parameter DSIZE = 1<<MSB_SLOT;
    parameter DEPTH = 1<<ADDRSIZE;



    reg [DEPTH-1:0] fifo_ff [DSIZE-1:0]; 
    reg [MSB_SLOT:0] write_ptr_ff,read_ptr_ff, next_write_ptr, next_read_ptr,fifo_ocup;

    always@*begin
        next_read_ptr = read_ptr_ff;
        next_write_ptr = write_ptr_ff;

        empty = (write_ptr_ff == read_ptr_ff);
        full = (write_ptr_ff[MSB_SLOT-1:0] == read_ptr_ff[MSB_SLOT-1:0] ) 
            && (write_ptr_ff[MSB_SLOT]!= read_ptr_ff[MSB_SLOT]);
                
        data_out = empty ? 0 : fifo_ff[read_ptr_ff[MSB_SLOT-1:0]];
        
        if (write_en && ~full)
            next_write_ptr = write_ptr_ff + 1'b1;

        if (read_en && ~empty)
            next_read_ptr = read_ptr_ff + 1'b1;

        error = (write_en && full) || (read_en && empty);
        fifo_ocup = write_ptr_ff - read_ptr_ff;
        ocup = fifo_ocup;
    end

    integer i;
    always@(posedge clk or posedge reset)begin
        if(reset) begin
            write_ptr_ff <= 1'b0;
            read_ptr_ff <= 1'b0;
            for (i = 0; i < 32; i = i + 1)
            begin
                fifo_ff[i] <= 0;       // Write zero to all registers
            end
        end
        else begin
            write_ptr_ff <= next_write_ptr;
            read_ptr_ff <= next_read_ptr;
            if (write_en && ~full)
                fifo_ff[write_ptr_ff[MSB_SLOT-1:0]] <= data_in;
        end
    end
endmodule

axi4/axi4lite_slave.v
/*

File: axi4lite_slave.v
Description: AXI4 lite slave interface to handle data 
    reads and writes in the Network interface. The interface allows for a 
    more general protocol to access the FIFO buffers used for reads and writes 
    in the NI. 



*/

module axi4lite_slave(
    
    input wire aclk,
    input wire arestn,
    
    // read address channel
    input wire [31:0] araddr,
    input wire arvalid,
    output reg arready,

    // read data channel
    output wire [31:0] rdata,
    output wire [1:0] rresp,
    output reg rvalid,
    input wire rready,

    // write address channel
    input wire [31:0] awaddr,
    input wire awvalid,
    output reg awready,

    // write data channel
    input wire [31:0] wdata,
    input wire wvalid,
    output wire wready,

    // write response
    output wire [1:0] bresp,
    output reg bvalid, 
    input wire bready,
    
    // For fifo access
    output wire read_en,
    input wire [31:0] read_data,
    input wire empty,

    output wire write_en,
    output wire [63:0] write_data,
    input wire full

);

    // rresp or bresp
    // 0b00 - OKAY
    // 0b01 - EXOKAY
    // 0b10 - SLVERR
    // 0b11 - DECERR

    /* Hanlding Write operation from Master

    - Master Puts data and address and asserts AWVALID, WVALID, BREADY
    - Slave asserts AWREADY and WRREADY when ready to accept. Master deasserts valid and ready on bothe address and data
    - ASsert BVALID 
    - Deassert both in BVALID and BREADY are high

    */

    /* Handling Read operation from Master

    - Read address, ARVALID, RREADY from master.
    - ARREADY by slave
    - ARVALID and ARREADY deasserted 
    - puts requested data on bus and RVALID
    - Since both RREADY and RVALID , deasserted

    */

    assign	reset = !arestn;
    assign	wready = awready;

    assign rresp = 2'b00;
    assign bresp = 2'b00;

    assign write_en = bvalid; 
    assign read_en = rvalid;

    initial	awready = 1'b0;
    initial	bvalid = 1'b0;
    initial rvalid = 1'b0;
    initial arready = 1'b0;

    assign write_data = {awaddr, wdata};
    assign rdata =  read_data;
    
    // assign arready = arvalid;

    // write operation
    always @ (posedge aclk)begin

        if(reset)
        begin
            bvalid <= 1'b0;
            // Clear FIFO
        end
        else if(wready)begin
            // write to FIFO        
            bvalid <= 1'b1;
        end
        else if(bready)//!bvalid
            bvalid <= 1'b0;
        
    end
    
    always @(posedge aclk)begin
        if(reset)
            awready <= 1'b0;
        else 
            awready <= !awready 
            && (awvalid && wvalid)
            && (!bvalid || bready);
    end


    // read operation 
    always@(posedge aclk)begin
        if (reset)begin
            arready =1'b0;
            rvalid <=1'b0; 
        end
        if (arvalid && !arready)
            arready <= 1'b1;
        if (arready)begin
            arready <= 1'b0;
            rvalid <=1'b1;
        end
        if (rready && rvalid)begin
            rvalid <= 1'b0;
        end
    end
    


/*
Instead of registers we are using fifo 
disregards address as reg address or fifo address. 
Can we use address to append to data and use the whole thing
to be stored in the fifo

Leaving strobe write out for this implementation

*/

endmodule

ni/ni.v
`include "../../axi4/axi4lite_slave.v"
`include "../../fifo/gp_fifo.v"

/*
File : ni.v
Description: This is the NoC side of things with a 
    axi4lite slave for core side and signals to send and recv 
    flits from NoC side. 
*/

module ni(
    
    input clk,
    input reset,

    // Should handle how write_en is generated 
    input wire [31:0] core_write_data,
    input wire [31:0] core_write_addr,
    input wire core_write_en,

    // Should handle how read_en is generated 
    // thresholed signal should be an output   
    output wire [31:0] core_read_data,
    // output wire [31:0] core_read_addr,
    input wire core_read_en

    // this will be an interrupt which in turn would handle the read_en
    // the threshold can be set to be of a packet size ?  
    // output wire [4:0] core_ocup
    
    // output wire core_empty,
    // output wire core_full,

    // output wire core_error,

);

    // Define Slave at input 
    // this will be the entry for NI 
    // handle master seperately 
    

    // // to be used by master axi4lite interface 
    // wire [31:0] axi4_write_data;
    // wire [31:0] axi4_write_addr;
    // wire axi4_write_en;

    // // to be used by master axi4lite interface
    // wire [31:0] axi4_read_data;
    // wire [31:0] axi4_read_addr;
    // wire axi4_read_en;

    // output wire axi4_full;
    // output wire axi4_empty;

    // output wire axi4_error,
    // output wire [4:0] axi4_ocup

    wire [63:0] core_data_in,core_data_out;//axi4_data_in,axi4_data_out;

    // [data , addr ]  => [MSB,LSB]
    // assign core_data_in[63:32] = core_write_data;
    // assign core_data_in[31:0]  = core_write_addr;

    // assign axi4_data_in[63:32] = axi4_write_data;
    // assign axi4_data_in[31:0]  = axi4_write_addr;
    
    // assign core_read_data = core_data_out[63:32];
    // assign core_read_addr = core_data_out[31:0];

    // assign axi4_read_data = axi4_data_out[63:32]; 
    // assign axi4_read_addr = axi4_data_out[31:0]; 

    reg awvalid,wvalid,bready;
    reg arvalid,rready;

    wire awready,wready,bvalid,arready,rvalid;
    wire [1:0] bresp,rresp;
    

    wire read_en, empty, write_en, full,error;
    wire [31:0] read_data;
    wire [63:0] write_data,read64_data;
    wire [4:0] ocup;

    assign read_data = read64_data[31:0];
    
    // creating axi4 master behaviour within ni
    always@(posedge clk)begin
        if(reset)begin
            awvalid = 1'b0;
            wvalid = 1'b0;
            bready = 1'b0;
        end
        if(core_write_en)begin 
            awvalid = 1'b1;
            wvalid = 1'b1;
            bready = 1'b1;
        end
        if(bready && bvalid)
            #2 bready = 1'b0;
        if(awvalid && awready)
            awvalid = 1'b0;
        if(wvalid && wready)
            wvalid = 1'b0;
        if(arvalid && arready)
            arvalid = 1'b0;
        if(rvalid && rready)
            rready = 1'b0;
    end

    always@(posedge clk)begin
        if(reset)begin
            arvalid = 1'b0;
            rready = 1'b0;
        end
        if(core_read_en)begin
            arvalid = 1'b1;
            rready = 1'b1;
        end
    end 

    axi4lite_slave slave(
        .aclk(clk),
        .arestn(!reset),
        
        // read address channel
        .araddr(32'h0),
        .arvalid(arvalid),
        .arready(arready),

        // read data channel
        .rdata(core_read_data),
        .rresp(rresp),
        .rvalid(rvalid),
        .rready(rready),

        // write address channel
        .awaddr(core_write_addr),
        .awvalid(awvalid),
        .awready(awready),

        // write data channel
        .wdata(core_write_data),
        .wvalid(wvalid),
        .wready(wready),

        // write response
        .bresp(bresp),
        .bvalid(bvalid), 
        .bready(bready),

        // For fifo access
        .read_en(read_en),
        .read_data(read_data),
        .empty(empty),

        .write_en(write_en),
        .write_data(write_data),
        .full(full)
    );


    // for testing going to read write to the same fifo
    // after verifying axi4lite slave modifies fifo as expected 
    // change to core and  ni read/write
    gp_fifo write_fifo (
        .clk(clk),
        .reset(reset),
        .write_en(write_en),
        .read_en(read_en),
        .data_in(write_data),
        .data_out(read64_data),
        .error(error),
        .full(full),
        .empty(empty),
        .ocup(ocup)
    );
    
    // gp_fifo read_fifo (
    //     .clk(clk),
    //     .reset(reset),
    //     .write_en(axi4_write_en),
    //     .read_en(core_read_en),
    //     .data_in(axi4_data_in),
    //     .data_out(core_data_out),
    //     .error(axi4_error),
    //     .full(core_full),
    //     .empty(axi4_empty),
    //     .ocup(core_ocup)
    // );
    

    // always@(posedge clk)begin
    //     //FIFO behaviour here for data exchange through slave
    // end


endmodule

tb/ni/ni_tb.v
`timescale 1ns / 1ps
`include "../../ni/ni.v"

module ni_tb();
    
    reg clk;
    reg reset;
    reg [31:0] core_write_data;
    reg [31:0] core_write_addr;
    reg core_write_en;
    reg core_read_en;
    wire [31:0] core_read_data;

    // Instantiate the FIFO module
    ni my_ni (
        .clk(clk),
        .reset(reset),
        .core_write_data(core_write_data),
        .core_write_addr(core_write_addr),
        .core_write_en(core_write_en),
        .core_read_data(core_read_data),
        .core_read_en(core_read_en)
    );

    integer i;
    // VCD dump file
    initial begin
        $dumpfile("ni_tb.vcd");
        $dumpvars(0, ni_tb);
        for(i = 0; i < 32; i = i + 1)
            $dumpvars(1, ni_tb.my_ni.write_fifo.fifo_ff[i]);

        // Initialize signals
        clk = 1;
        reset = 1;
        core_write_en = 1'b0;
        core_read_en = 1'b0;
        core_write_addr = 32'h0;
        core_write_data = 32'h0;

        #20;
        // Release reset
        reset = 1'b0;
        // Write data to the FIFO
        core_write_en = 1'b1;
        core_read_en = 1'b0;
        core_write_addr = 32'hA5A5A5A5;
        core_write_data = 32'hAAAAAAAA;

        #20;

        core_write_en = 1'b0;
        core_read_en = 1'b1;
        core_write_addr = 32'h0;
        core_write_data = 32'h0;

        #20;
        reset = 1;
        core_write_en = 1'b0;
        core_read_en = 1'b0;
        core_write_addr = 32'h0;
        core_write_data = 32'h0;

        #10;
        reset = 0;
        // Perform additional read and write operations as needed
        // End simulation
        $finish;
    end

    // Clock generation
    always begin
        #5 clk = ~clk;
    end

endmodule

tb/ni/ni_tb.vcd
$date
	Sun Nov 19 12:05:39 2023
$end
$version
	Icarus Verilog
$end
$timescale
	1ps
$end
$scope module ni_tb $end
$var wire 32 ! core_read_data [31:0] $end
$var reg 1 " clk $end
$var reg 1 # core_read_en $end
$var reg 32 $ core_write_addr [31:0] $end
$var reg 32 % core_write_data [31:0] $end
$var reg 1 & core_write_en $end
$var reg 1 ' reset $end
$var integer 32 ( i [31:0] $end
$scope module my_ni $end
$var wire 2 ) bresp [1:0] $end
$var wire 1 " clk $end
$var wire 1 # core_read_en $end
$var wire 32 * core_write_addr [31:0] $end
$var wire 32 + core_write_data [31:0] $end
$var wire 1 & core_write_en $end
$var wire 1 ' reset $end
$var wire 2 , rresp [1:0] $end
$var wire 1 - write_en $end
$var wire 64 . write_data [63:0] $end
$var wire 1 / wready $end
$var wire 1 0 rvalid $end
$var wire 1 1 read_en $end
$var wire 32 2 read_data [31:0] $end
$var wire 64 3 read64_data [63:0] $end
$var wire 5 4 ocup [4:0] $end
$var wire 1 5 full $end
$var wire 1 6 error $end
$var wire 1 7 empty $end
$var wire 32 8 core_read_data [31:0] $end
$var wire 1 9 bvalid $end
$var wire 1 : awready $end
$var wire 1 ; arready $end
$var reg 1 < arvalid $end
$var reg 1 = awvalid $end
$var reg 1 > bready $end
$var reg 1 ? rready $end
$var reg 1 @ wvalid $end
$scope module slave $end
$var wire 1 " aclk $end
$var wire 32 A araddr [31:0] $end
$var wire 1 B arestn $end
$var wire 1 < arvalid $end
$var wire 32 C awaddr [31:0] $end
$var wire 1 = awvalid $end
$var wire 1 > bready $end
$var wire 2 D bresp [1:0] $end
$var wire 32 E rdata [31:0] $end
$var wire 32 F read_data [31:0] $end
$var wire 1 1 read_en $end
$var wire 1 ? rready $end
$var wire 2 G rresp [1:0] $end
$var wire 32 H wdata [31:0] $end
$var wire 1 / wready $end
$var wire 1 - write_en $end
$var wire 1 @ wvalid $end
$var wire 64 I write_data [63:0] $end
$var wire 1 J reset $end
$var wire 1 5 full $end
$var wire 1 7 empty $end
$var reg 1 ; arready $end
$var reg 1 : awready $end
$var reg 1 9 bvalid $end
$var reg 1 0 rvalid $end
$upscope $end
$scope module write_fifo $end
$var wire 1 " clk $end
$var wire 64 K data_in [63:0] $end
$var wire 1 1 read_en $end
$var wire 1 ' reset $end
$var wire 1 - write_en $end
$var reg 64 L data_out [63:0] $end
$var reg 1 7 empty $end
$var reg 1 6 error $end
$var reg 6 M fifo_ocup [5:0] $end
$var reg 1 5 full $end
$var reg 6 N next_read_ptr [5:0] $end
$var reg 6 O next_write_ptr [5:0] $end
$var reg 5 P ocup [4:0] $end
$var reg 6 Q read_ptr_ff [5:0] $end
$var reg 6 R write_ptr_ff [5:0] $end
$var integer 32 S i [31:0] $end
$upscope $end
$upscope $end
$upscope $end
$scope module ni_tb $end
$scope module my_ni $end
$scope module write_fifo $end
$var reg 64 T \fifo_ff[0] [63:0] $end
$upscope $end
$upscope $end
$upscope $end
$scope module ni_tb $end
$scope module my_ni $end
$scope module write_fifo $end
$var reg 64 U \fifo_ff[1] [63:0] $end
$upscope $end
$upscope $end
$upscope $end
$scope module ni_tb $end
$scope module my_ni $end
$scope module write_fifo $end
$var reg 64 V \fifo_ff[2] [63:0] $end
$upscope $end
$upscope $end
$upscope $end
$scope module ni_tb $end
$scope module my_ni $end
$scope module write_fifo $end
$var reg 64 W \fifo_ff[3] [63:0] $end
$upscope $end
$upscope $end
$upscope $end
$scope module ni_tb $end
$scope module my_ni $end
$scope module write_fifo $end
$var reg 64 X \fifo_ff[4] [63:0] $end
$upscope $end
$upscope $end
$upscope $end
$scope module ni_tb $end
$scope module my_ni $end
$scope module write_fifo $end
$var reg 64 Y \fifo_ff[5] [63:0] $end
$upscope $end
$upscope $end
$upscope $end
$scope module ni_tb $end
$scope module my_ni $end
$scope module write_fifo $end
$var reg 64 Z \fifo_ff[6] [63:0] $end
$upscope $end
$upscope $end
$upscope $end
$scope module ni_tb $end
$scope module my_ni $end
$scope module write_fifo $end
$var reg 64 [ \fifo_ff[7] [63:0] $end
$upscope $end
$upscope $end
$upscope $end
$scope module ni_tb $end
$scope module my_ni $end
$scope module write_fifo $end
$var reg 64 \ \fifo_ff[8] [63:0] $end
$upscope $end
$upscope $end
$upscope $end
$scope module ni_tb $end
$scope module my_ni $end
$scope module write_fifo $end
$var reg 64 ] \fifo_ff[9] [63:0] $end
$upscope $end
$upscope $end
$upscope $end
$scope module ni_tb $end
$scope module my_ni $end
$scope module write_fifo $end
$var reg 64 ^ \fifo_ff[10] [63:0] $end
$upscope $end
$upscope $end
$upscope $end
$scope module ni_tb $end
$scope module my_ni $end
$scope module write_fifo $end
$var reg 64 _ \fifo_ff[11] [63:0] $end
$upscope $end
$upscope $end
$upscope $end
$scope module ni_tb $end
$scope module my_ni $end
$scope module write_fifo $end
$var reg 64 ` \fifo_ff[12] [63:0] $end
$upscope $end
$upscope $end
$upscope $end
$scope module ni_tb $end
$scope module my_ni $end
$scope module write_fifo $end
$var reg 64 a \fifo_ff[13] [63:0] $end
$upscope $end
$upscope $end
$upscope $end
$scope module ni_tb $end
$scope module my_ni $end
$scope module write_fifo $end
$var reg 64 b \fifo_ff[14] [63:0] $end
$upscope $end
$upscope $end
$upscope $end
$scope module ni_tb $end
$scope module my_ni $end
$scope module write_fifo $end
$var reg 64 c \fifo_ff[15] [63:0] $end
$upscope $end
$upscope $end
$upscope $end
$scope module ni_tb $end
$scope module my_ni $end
$scope module write_fifo $end
$var reg 64 d \fifo_ff[16] [63:0] $end
$upscope $end
$upscope $end
$upscope $end
$scope module ni_tb $end
$scope module my_ni $end
$scope module write_fifo $end
$var reg 64 e \fifo_ff[17] [63:0] $end
$upscope $end
$upscope $end
$upscope $end
$scope module ni_tb $end
$scope module my_ni $end
$scope module write_fifo $end
$var reg 64 f \fifo_ff[18] [63:0] $end
$upscope $end
$upscope $end
$upscope $end
$scope module ni_tb $end
$scope module my_ni $end
$scope module write_fifo $end
$var reg 64 g \fifo_ff[19] [63:0] $end
$upscope $end
$upscope $end
$upscope $end
$scope module ni_tb $end
$scope module my_ni $end
$scope module write_fifo $end
$var reg 64 h \fifo_ff[20] [63:0] $end
$upscope $end
$upscope $end
$upscope $end
$scope module ni_tb $end
$scope module my_ni $end
$scope module write_fifo $end
$var reg 64 i \fifo_ff[21] [63:0] $end
$upscope $end
$upscope $end
$upscope $end
$scope module ni_tb $end
$scope module my_ni $end
$scope module write_fifo $end
$var reg 64 j \fifo_ff[22] [63:0] $end
$upscope $end
$upscope $end
$upscope $end
$scope module ni_tb $end
$scope module my_ni $end
$scope module write_fifo $end
$var reg 64 k \fifo_ff[23] [63:0] $end
$upscope $end
$upscope $end
$upscope $end
$scope module ni_tb $end
$scope module my_ni $end
$scope module write_fifo $end
$var reg 64 l \fifo_ff[24] [63:0] $end
$upscope $end
$upscope $end
$upscope $end
$scope module ni_tb $end
$scope module my_ni $end
$scope module write_fifo $end
$var reg 64 m \fifo_ff[25] [63:0] $end
$upscope $end
$upscope $end
$upscope $end
$scope module ni_tb $end
$scope module my_ni $end
$scope module write_fifo $end
$var reg 64 n \fifo_ff[26] [63:0] $end
$upscope $end
$upscope $end
$upscope $end
$scope module ni_tb $end
$scope module my_ni $end
$scope module write_fifo $end
$var reg 64 o \fifo_ff[27] [63:0] $end
$upscope $end
$upscope $end
$upscope $end
$scope module ni_tb $end
$scope module my_ni $end
$scope module write_fifo $end
$var reg 64 p \fifo_ff[28] [63:0] $end
$upscope $end
$upscope $end
$upscope $end
$scope module ni_tb $end
$scope module my_ni $end
$scope module write_fifo $end
$var reg 64 q \fifo_ff[29] [63:0] $end
$upscope $end
$upscope $end
$upscope $end
$scope module ni_tb $end
$scope module my_ni $end
$scope module write_fifo $end
$var reg 64 r \fifo_ff[30] [63:0] $end
$upscope $end
$upscope $end
$upscope $end
$scope module ni_tb $end
$scope module my_ni $end
$scope module write_fifo $end
$var reg 64 s \fifo_ff[31] [63:0] $end
$upscope $end
$upscope $end
$upscope $end
$enddefinitions $end
#0
$dumpvars
b0 s
b0 r
b0 q
b0 p
b0 o
b0 n
b0 m
b0 l
b0 k
b0 j
b0 i
b0 h
b0 g
b0 f
b0 e
b0 d
b0 c
b0 b
b0 a
b0 `
b0 _
b0 ^
b0 ]
b0 \
b0 [
b0 Z
b0 Y
b0 X
b0 W
b0 V
b0 U
b0 T
b100000 S
b0 R
b0 Q
b0 P
b0 O
b0 N
b0 M
b0 L
b0 K
1J
b0 I
b0 H
b0 G
b0 F
b0 E
b0 D
b0 C
0B
b0 A
0@
0?
0>
0=
0<
0;
0:
09
b0 8
17
06
05
b0 4
b0 3
b0 2
01
00
0/
b0 .
0-
b0 ,
b0 +
b0 *
b0 )
b100000 (
1'
0&
b0 %
b0 $
0#
1"
b0 !
$end
#5000
0"
#10000
b0 s
b0 r
b0 q
b0 p
b0 o
b0 n
b0 m
b0 l
b0 k
b0 j
b0 i
b0 h
b0 g
b0 f
b0 e
b0 d
b0 c
b0 b
b0 a
b0 `
b0 _
b0 ^
b0 ]
b0 \
b0 [
b0 Z
b0 Y
b0 X
b0 W
b0 V
b0 U
b0 T
b100000 S
1"
#15000
0"
#20000
1/
1:
1>
1@
1=
1"
b10101010101010101010101010101010 %
b10101010101010101010101010101010 +
b10101010101010101010101010101010 H
b1010010110100101101001011010010110101010101010101010101010101010 .
b1010010110100101101001011010010110101010101010101010101010101010 I
b1010010110100101101001011010010110101010101010101010101010101010 K
b10100101101001011010010110100101 $
b10100101101001011010010110100101 *
b10100101101001011010010110100101 C
1&
0J
1B
0'
#25000
0"
#30000
b1 O
0/
0:
1-
19
0@
0=
1"
#35000
0"
#40000
b1 4
b1 P
b1 M
07
0-
09
1;
b0 T
b1 R
1?
1<
1"
b0 %
b0 +
b0 H
b0 .
b0 I
b0 K
b0 $
b0 *
b0 C
1#
0&
#42000
0<
0>
#45000
0"
#50000
b1 N
11
10
0;
1<
1"
#55000
0"
#60000
b0 4
b0 P
b0 M
17
b0 O
b0 N
01
00
b0 s
b0 r
b0 q
b0 p
b0 o
b0 n
b0 m
b0 l
b0 k
b0 j
b0 i
b0 h
b0 g
b0 f
b0 e
b0 d
b0 c
b0 b
b0 a
b0 `
b0 _
b0 ^
b0 ]
b0 \
b0 [
b0 Z
b0 Y
b0 X
b0 W
b0 V
b0 U
b0 T
b0 R
0?
0<
b100000 S
1"
0#
1J
0B
1'
#65000
0"
#70000
1"
0J
1B
0'
