axi4/axi4lite_master.v
// `include "../ni/fifo_32x64"

module axi4lite_master(
    
    input wire aclk,
    input wire arestn,
    
    // read address channel
    output wire [31:0] araddr,
    output wire arvalid,
    input wire arready,

    // read data channel
    input wire [31:0] rdata,
    input wire [1:0] rresp,
    input wire rvalid,
    output wire rready,

    // write address channel
    output wire [31:0] awaddr,
    output wire awvalid,
    input wire awready,

    // write data channel
    output wire [31:0] wdata,
    output wire wvalid,
    input wire wready,

    // write response
    input wire [1:0] bresp,
    input wire bvalid, 
    output wire bready
    

    
    
);

// rresp or bresp
// 0b00 - OKAY
// 0b01 - EXOKAY
// 0b10 - SLVERR
// 0b11 - DECERR




endmodule

fifo/gp_fifo.v
/*

File: gp_fifo.v
Descripton: Simple FIFO module

General purpose FIFO to handle the read and write buffer.
The whole FIFO runs on the same clock domain (ie. not the async version )

32 slots of 64 bits

*/

module gp_fifo(
    input clk,
    input reset,
    input write_en,
    input read_en,
    input [63:0] data_in,
    output reg [63:0] data_out,
    output reg error,
    output reg full,
    output reg empty,
    output reg [4:0] ocup
);

    // this is one less than MSB (32bit -> 5 )
    `define MSB_SLOT 4

    reg [63:0] fifo_ff [31:0]; 
    reg [`MSB_SLOT:0] write_ptr_ff,read_ptr_ff, next_write_ptr, next_read_ptr,fifo_ocup;

    always@*begin
        next_read_ptr = read_ptr_ff;
        next_write_ptr = write_ptr_ff;

        empty = (write_ptr_ff == read_ptr_ff);
        full = (write_ptr_ff[`MSB_SLOT-1:0] == read_ptr_ff[`MSB_SLOT-1:0] )  && (write_ptr_ff[`MSB_SLOT]!= read_ptr_ff[`MSB_SLOT]);
                
        data_out = empty ? 0 : fifo_ff[read_ptr_ff[`MSB_SLOT-1:0]];
        
        if (write_en && ~full)
            next_write_ptr = write_ptr_ff + 1'b1;

        if (read_en && ~empty)
            next_read_ptr = read_ptr_ff + 1'b1;

        error = (write_en && full) || (read_en && empty);
        fifo_ocup = write_ptr_ff - read_ptr_ff;
        ocup = fifo_ocup;
    end

    integer i;
    always@(posedge clk or posedge reset)begin
        if(reset) begin
            write_ptr_ff <= 1'b0;
            read_ptr_ff <= 1'b0;
            for (i = 0; i < 32; i = i + 1)
            begin
                fifo_ff[i] <= 0;       // Write zero to all registers
            end
        end
        else begin
            write_ptr_ff <= next_write_ptr;
            read_ptr_ff <= next_read_ptr;
            if (write_en && ~full)
                fifo_ff[write_ptr_ff[`MSB_SLOT-1:0]] <= data_in;
        end
    end
endmodule

axi4/axi4lite_slave.v
module axi4lite_slave(
    
    input wire aclk,
    input wire arestn,
    
    // read address channel
    input wire [31:0] araddr,
    input wire arvalid,
    output reg arready,

    // read data channel
    output wire [31:0] rdata,
    output wire [1:0] rresp,
    output reg rvalid,
    input wire rready,

    // write address channel
    input wire [31:0] awaddr,
    input wire awvalid,
    output reg awready,

    // write data channel
    input wire [31:0] wdata,
    input wire wvalid,
    output wire wready,

    // write response
    output wire [1:0] bresp,
    output reg bvalid, 
    input wire bready,
    
    // For fifo access
    output wire read_en,
    input wire [31:0] read_data,
    input wire empty,

    output wire write_en,
    output wire [63:0] write_data,
    input wire full

);

    // rresp or bresp
    // 0b00 - OKAY
    // 0b01 - EXOKAY
    // 0b10 - SLVERR
    // 0b11 - DECERR



    /* Hanlding Write operation from Master

    - Master Puts data and address and asserts AWVALID, WVALID, BREADY
    - Slave asserts AWREADY and WRREADY when ready to accept. Master deasserts valid and ready on bothe address and data
    - ASsert BVALID 
    - Deassert both in BVALID and BREADY are high

    */



    /* Handling Read operation from Master

    - Read address, ARVALID, RREADY from master.
    - ARREADY by slave
    - ARVALID and ARREADY deasserted 
    - puts requested data on bus and RVALID
    - Since both RREADY and RVALID , deasserted

    */

    assign	reset = !arestn;
    assign	wready = awready;

    assign rresp = 2'b00;
    assign bresp = 2'b00;


    assign write_en = bvalid; 
    assign read_en = rvalid;

    initial	awready = 1'b0;
    initial	bvalid = 1'b0;
    initial rvalid = 1'b0;
    initial arready = 1'b0;



    assign write_data = {awaddr, wdata};
    assign rdata =  read_data;
    // write operation
    always @ (posedge aclk)begin

        if(reset)
        begin
            bvalid <= 1'b0;
            rvalid <=1'b0; 
            // Clear FIFO
        end
        else if(wready)begin
            // write to FIFO        
            bvalid <= 1'b1;
        end
        else if(bready && bvalid)
            bvalid <= 1'b0;
        
    end
    
    always @(posedge aclk)begin
        if(reset)
            awready <= 1'b0;
        else 
            awready <= !awready 
            && (awvalid && wvalid)
            && (!bvalid || bready);
    end


    // read operation 
    always@(posedge aclk)begin
        if (reset)begin
            arready =1'b0;
        end
        if (arvalid)
            arready <= 1'b1;
        if (arvalid && arready)begin
            arready <= 1'b0;
            rvalid <=1'b1;
        end
        else if (rready && rvalid)begin
            rvalid <= 1'b0;
        end
    end
    


/*
Instead of registers we are using fifo 
disregards address as reg address or fifo address. 
Can we use address to append to data and use the whole thing
to be stored in the fifo

Leaving strobe write out for this implementation

*/

endmodule

ni/ni.v
`include "../../axi4/axi4lite_master.v"
`include "../../axi4/axi4lite_slave.v"
`include "../../ni/gp_fifo.v"

/*
File : ni.v
Description: This is the NoC side of things with a 
    axi4lite slave for core side and signals to send and recv 
    flits from NoC side. 
*/

module ni(
    
    input clk,
    input reset,

    // Should handle how write_en is generated 
    input wire [31:0] core_write_data,
    input wire [31:0] core_write_addr,
    input wire core_write_en,

    // Should handle how read_en is generated 
    // thresholed signal should be an output   
    output wire [31:0] core_read_data,
    output wire [31:0] core_read_addr,
    input wire core_read_en,

    // this will be an interrupt which in turn would handle the read_en
    // the threshold can be set to be of a packet size ?  
    output wire [4:0] core_ocup
    
    output wire core_empty,
    output wire core_full,

    output wire core_error,

);


    // Define Slave at input 
    // this will be the entry for NI 
    // handle master seperately 
    

    // to be used by master axi4lite interface 
    input wire [31:0] axi4_write_data;
    input wire [31:0] axi4_write_addr;
    input wire axi4_write_en;

    // to be used by master axi4lite interface
    output wire [31:0] axi4_read_data;
    output wire [31:0] axi4_read_addr;
    input wire axi4_read_en;

    output wire axi4_full;
    output wire axi4_empty;

    output wire axi4_error,
    output wire [4:0] axi4_ocup

    wire [63:0] core_data_in,core_data_out,axi4_data_in,axi4_data_out;

    // [data , addr ]  => [MSB,LSB]
    assign core_data_in[63:32] = core_write_data;
    assign core_data_in[31:0]  = core_write_addr;

    assign axi4_data_in[63:32] = axi4_write_data;
    assign axi4_data_in[31:0]  = axi4_write_addr;
    
    assign core_read_data =  core_data_out[63:32];
    assign core_read_addr =  core_data_out[31:0];

    assign axi4_read_data = axi4_data_out[63:32]; 
    assign axi4_read_addr = axi4_data_out[31:0]; 

    axi4lite_slave slave(
        .aclk(clk),
        .arestn(~reset),
        
        // read address channel
        .araddr(araddr),
        .arvalid(arvalid),
        arready(arready),

        // read data channel
        .rdata(rdata),
        .rresp(rresp),
        .rvalid(rvalid),
        .rready(rready),

        // write address channel
        .awaddr(awaddr),
        .awvalid(awvalid),
        .awready(awready),

        // write data channel
        .wdata(wdata),
        .wvalid(wvalid),
        .wready(wready),

        // write response
        .bresp(bresp),
        .bvalid(bvalid), 
        .bready(bready)
    );


    gp_fifo write_fifo (
        .clk(clk),
        .reset(reset),
        .write_en(core_write_en),
        .read_en(axi4_read_en),
        .data_in(core_data_in),
        .data_out(axi4_data_out),
        .error(core_error),
        .full(axi4_full),
        .empty(core_empty),
        .ocup(axi4_ocup)
    );
    
    gp_fifo read_fifo (
        .clk(clk),
        .reset(reset),
        .write_en(axi4_write_en),
        .read_en(core_read_en),
        .data_in(axi4_data_in),
        .data_out(core_data_out),
        .error(axi4_error),
        .full(core_full),
        .empty(axi4_empty),
        .ocup(core_ocup)
    );
    




endmodule

tb/axi4/axi4lite_slave_tb.v
`timescale 1ns / 1ps
`include "../../ni/ni.v"

module ni_tb();
    
    reg clk;
    reg reset;
    reg [31:0] core_write_data;
    reg [31:0] core_write_addr;
    reg core_write_en;
    wire core_empty;
    wire core_error;
    
    wire [31:0] axi4_read_data;
    reg [31:0] axi4_read_addr;
    reg axi4_read_en;
    wire axi4_full;
    wire [4:0] axi4_ocup;

    // Instantiate the FIFO module
    ni my_ni (
        .clk(clk),
        .reset(reset),
        .core_write_data(core_write_data),
        .core_write_addr(core_write_addr),
        .core_write_en(core_write_en),
        .core_empty(core_empty),
        .core_error(core_error),
        .axi4_read_data(axi4_read_data),
        .axi4_read_addr(axi4_read_addr),
        .axi4_read_en(axi4_read_en),
        .axi4_full(axi4_full),
        .axi4_ocup(axi4_ocup)
    );

    // VCD dump file
    initial begin
        $dumpfile("ni_tb.vcd");
        $dumpvars(0, ni_tb);

        // Initialize signals
        clk = 0;
        reset = 1;
        core_write_en = 1'b0;
        axi4_read_en = 1'b0;
        core_write_data = 32'h0;
        core_write_data = 32'h0;

        #20;
        // Release reset
        reset = 1'b0;
        // Write data to the FIFO
        core_write_en = 1'b0;
        core_write_data = 64'hA5A5A5A5A5A5A5A5; // Example data
        #10;
        // Release reset
        reset = 1'b0;
        // Write data to the FIFO
        core_write_en = 1;
        core_write_data = 64'hA5A5A5A5A5A5A5A5; // Example data

        #10;
        // Release reset
        reset = 1'b0;
        // Write data to the FIFO
        core_write_en = 1;
        core_write_data = 64'hA5A5A5A5A5A5A1A5; // Example data


        #10;
        core_write_en = 0;
        // Read data from the FIFO
        axi4_read_en = 1;

        #10;
        // Perform additional read and write operations as needed
        // End simulation
        $finish;
    end

    // Clock generation
    always begin
        #5 clk = ~clk;
    end

endmodule

tb/ni/ni_tb.vcd
$date
	Sun Nov  5 08:39:56 2023
$end
$version
	Icarus Verilog
$end
$timescale
	1ps
$end
$scope module ni_tb $end
$var wire 1 ! core_error $end
$var wire 1 " core_empty $end
$var wire 32 # axi4_read_data [31:0] $end
$var wire 5 $ axi4_ocup [4:0] $end
$var wire 1 % axi4_full $end
$var reg 32 & axi4_read_addr [31:0] $end
$var reg 1 ' axi4_read_en $end
$var reg 1 ( clk $end
$var reg 32 ) core_write_addr [31:0] $end
$var reg 32 * core_write_data [31:0] $end
$var reg 1 + core_write_en $end
$var reg 1 , reset $end
$scope module my_ni $end
$var wire 32 - axi4_read_addr [31:0] $end
$var wire 1 ' axi4_read_en $end
$var wire 1 ( clk $end
$var wire 32 . core_write_addr [31:0] $end
$var wire 32 / core_write_data [31:0] $end
$var wire 1 + core_write_en $end
$var wire 1 , reset $end
$var wire 1 ! core_error $end
$var wire 1 " core_empty $end
$var wire 32 0 axi4_read_data [31:0] $end
$var wire 5 1 axi4_ocup [4:0] $end
$var wire 1 % axi4_full $end
$scope module write_fifo $end
$var wire 1 ( clk $end
$var wire 64 2 data_in [63:0] $end
$var wire 1 ' read_en $end
$var wire 1 , reset $end
$var wire 1 + write_en $end
$var reg 64 3 data_out [63:0] $end
$var reg 1 " empty $end
$var reg 1 ! error $end
$var reg 5 4 fifo_ocup [4:0] $end
$var reg 1 % full $end
$var reg 5 5 next_read_ptr [4:0] $end
$var reg 5 6 next_write_ptr [4:0] $end
$var reg 5 7 ocup [4:0] $end
$var reg 5 8 read_ptr_ff [4:0] $end
$var reg 5 9 write_ptr_ff [4:0] $end
$var integer 32 : i [31:0] $end
$upscope $end
$upscope $end
$upscope $end
$enddefinitions $end
#0
$dumpvars
b100000 :
b0 9
b0 8
b0 7
b0 6
b0 5
b0 4
b0 3
b0 2
b0 1
b0 0
b0 /
bx .
bx -
1,
0+
b0 *
bx )
0(
0'
bx &
0%
b0 $
b0 #
1"
0!
$end
#5000
b100000 :
1(
#10000
0(
#15000
b100000 :
1(
#20000
0(
b10100101101001011010010110100101 2
b10100101101001011010010110100101 *
b10100101101001011010010110100101 /
0,
#25000
1(
#30000
b1 6
0(
1+
#35000
b10100101101001011010010110100101 #
b10100101101001011010010110100101 0
b1 $
b1 1
b1 7
b1 4
b10 6
b10100101101001011010010110100101 3
0"
b1 9
1(
#40000
0(
b10100101101001011010000110100101 2
b10100101101001011010000110100101 *
b10100101101001011010000110100101 /
#45000
b10 $
b10 1
b10 7
b10 4
b11 6
b10 9
1(
#50000
b1 5
b10 6
0(
1'
0+
#55000
b10100101101001011010000110100101 #
b10100101101001011010000110100101 0
b1 $
b1 1
b1 7
b1 4
b10 5
b10100101101001011010000110100101 3
b1 8
1(
