utils/mux_5to1.v
module mux_5to1 (
  input wire [0:4] data_inputs, // 4 input lines
  input wire [2:0] ctrl,        // 2-bit control signal
  output wire mux_output
);

  assign mux_output = (ctrl == 3'b000) ? data_inputs[0] :
                     (ctrl == 3'b001) ? data_inputs[1] :
                     (ctrl == 3'b010) ? data_inputs[2] :
                     (ctrl == 3'b011) ? data_inputs[3] :
                     (ctrl == 3'b100) ? data_inputs[4] :
                     1'bz; // Output is tri-stated when control value is invalid

endmodule

utils/rr_arbiter.v
/*

File:  rr_arbiter.v
Descripton: Arbiter to chose between vc buffers which to 
output. 

Check before rrarbiter choice if data available
if not empty && rrarbiter 


The arbiter has an FSM to cycle throough the choices

*/

module rr_arbiter(
  input wire clk,
  input wire reset,
  input wire [4:0] request, // 5 request inputs
  output reg [2:0] grant
);

  // for grant 
  `define N 3'b000
  `define S 3'b001
  `define E 3'b010
  `define W 3'b011
  `define L 3'b100
  `define INVALID 3'b111

  reg [2:0] state;
  reg [2:0] next_state;

  // check what count is for
  reg [1:0] count;
  

  parameter [2:0] s_ideal = 3'b101 ;
  parameter [2:0] s0 = 3'b000 ;
  parameter [2:0] s1 = 3'b001 ;
  parameter [2:0] s2 = 3'b010 ;
  parameter [2:0] s3 = 3'b011 ;
  parameter [2:0] s4 = 3'b100 ; 

  always @ (posedge clk or posedge reset)begin
    if(reset) 
      state <= s_ideal;
    else
      state <= next_state;
  end

  initial state = s_ideal;

  always @ (state, next_state)begin
    case(state)
      s_ideal: begin
        if (request[0])begin
          next_state = s0;
        end
        else if (request[1])begin
          next_state = s1;
        end
        else if (request[2])begin
          next_state = s2;
        end
        else if (request[3])begin
          next_state = s3;
        end
        else if (request[4])begin
          next_state = s4;
        end
        else begin
          next_state = s_ideal;
        end
      end
      s0: begin
        if (request[1])begin
          next_state = s1;
        end
        else if (request[2])begin
          next_state = s2;
        end
        else if (request[3])begin
          next_state = s3;
        end
        else if (request[4])begin
          next_state = s4;
        end
        else if (request[0])begin
          next_state = s0;
        end
        else begin
          next_state = s_ideal;
        end
      end
      s1: begin
        if (request[2])begin
          next_state = s2;
        end
        else if (request[3])begin
          next_state = s3;
        end
        else if (request[4])begin
          next_state = s4;
        end
        else if (request[0])begin
          next_state = s0;
        end
        else if (request[1])begin
          next_state = s1;
        end
        else begin
          next_state = s_ideal;
        end
      end
      s2: begin
        if (request[3])begin
          next_state = s3;
        end
        else if (request[4])begin
          next_state = s4;
        end
        else if (request[0])begin
          next_state = s0;
        end
        else if (request[1])begin
          next_state = s1;
        end
        else if (request[2])begin
          next_state = s2;
        end
        else begin
          next_state = s_ideal;
        end
      end
      s3: begin
        if (request[4])begin
          next_state = s4;
        end
        else if (request[0])begin
          next_state = s0;
        end
        else if (request[1])begin
          next_state = s1;
        end
        else if (request[2])begin
          next_state = s2;
        end
        else if (request[3])begin
          next_state = s3;
        end
        else begin
          next_state = s_ideal;
        end
      end
      s4: begin
        if (request[0])begin
          next_state = s0;
        end
        else if (request[1])begin
          next_state = s1;
        end
        else if (request[2])begin
          next_state = s2;
        end
        else if (request[3])begin
          next_state = s3;
        end
        else if (request[4])begin
          next_state = s4;
        end
        else begin
          next_state = s_ideal;
        end
      end
      default: begin
        if (request[0])begin
          next_state = s0;
        end
        else if (request[1])begin
          next_state = s1;
        end
        else if (request[2])begin
          next_state = s2;
        end
        else if (request[3])begin
          next_state = s3;
        end
        else if (request[4])begin
          next_state = s4;
        end
        else begin
          next_state = s_ideal;
        end
      end

    endcase
  end  
  

  always @(state)
    begin
      case(state)
        s0: begin grant=`N; end
        s1: begin grant=`S; end
        s2: begin grant=`E; end
        s3: begin grant=`W; end
        s4: begin grant=`L; end
        default: begin grant = `INVALID; end
    end
  endmodule

endmodule

fifo/vc_buffer.v
/*

File: vc_buffer.v
Descripton: virtual channel buffer derived from FIFO module

Same as general purpose FIFO all reads and writes 
happen within a same clock domain


*/
module vc_buffer(
    input clk,
    input reset,
    input write_en,
    input read_en,
    input [DEPTH-1:0] data_in,
    output reg [DEPTH-1:0] data_out,
    output reg error,
    output reg full,
    output reg empty,
    output reg [MSB_SLOT-1:0] ocup
);


    parameter MSB_SLOT = 5;
    parameter ADDRSIZE = 5;
    parameter DSIZE = 1<<MSB_SLOT;
    parameter DEPTH = 1<<ADDRSIZE;



    reg [DEPTH-1:0] fifo_ff [DSIZE-1:0]; 
    reg [MSB_SLOT:0] write_ptr_ff,read_ptr_ff, next_write_ptr, next_read_ptr,fifo_ocup;

    always@*begin
        next_read_ptr = read_ptr_ff;
        next_write_ptr = write_ptr_ff;

        empty = (write_ptr_ff == read_ptr_ff);
        full = (write_ptr_ff[MSB_SLOT-1:0] == read_ptr_ff[MSB_SLOT-1:0] ) 
            && (write_ptr_ff[MSB_SLOT]!= read_ptr_ff[MSB_SLOT]);
                
        data_out = empty ? 0 : fifo_ff[read_ptr_ff[MSB_SLOT-1:0]];
        
        if (write_en && ~full)
            next_write_ptr = write_ptr_ff + 1'b1;

        if (read_en && ~empty)
            next_read_ptr = read_ptr_ff + 1'b1;

        error = (write_en && full) || (read_en && empty);
        fifo_ocup = write_ptr_ff - read_ptr_ff;
        ocup = fifo_ocup;
    end

    integer i;
    always@(posedge clk or posedge reset)begin
        if(reset) begin
            write_ptr_ff <= 1'b0;
            read_ptr_ff <= 1'b0;
            for (i = 0; i < 32; i = i + 1)
            begin
                fifo_ff[i] <= 0;       // Write zero to all registers
            end
        end
        else begin
            write_ptr_ff <= next_write_ptr;
            read_ptr_ff <= next_read_ptr;
            if (write_en && ~full)
                fifo_ff[write_ptr_ff[MSB_SLOT-1:0]] <= data_in;
        end
    end
endmodule

utils/demux_1to5.v
module demux_1to5 (
  input wire data_input,  // Input data to be demultiplexed
  input wire [2:0] ctrl,        // Control signal to select an output
  output wire out0,       // Demuxed output 0
  output wire out1,       // Demuxed output 1
  output wire out2,       // Demuxed output 2
  output wire out3,        // Demuxed output 3
  output wire out4        // Demuxed output 3
);

  assign out0 = (ctrl == 3'b000) ? data_input : 1'b0;
  assign out1 = (ctrl == 3'b001) ? data_input : 1'b0;
  assign out2 = (ctrl == 3'b010) ? data_input : 1'b0;
  assign out3 = (ctrl == 3'b011) ? data_input : 1'b0;
  assign out4 = (ctrl == 3'b100) ? data_input : 1'b0;

endmodule

input_module/input_router.v
/*

File: input_router.v
Descripton: input router module that does the route calculation 

Only does below if head flit

Here the route algorithm calculates 
the VC buffer the cosidered flit should be passed to 

The VC buffers here are used as 
buffers for the four directions 

Compare with x and y position of the contained router
port is inputted to be ignored


DOES NOT ACCOUNT FOR SAME PORT JUST YET -> Now it happens!! gives out invalid 
both xy and yx tested

The PORT , ROUTER_X, ROUTER_Y, akgorithm is set as parameters for the input router
For each data_in check dest_x and dest_y to find vc_select

*/

module input_router(
    input wire clk, 
    input wire reset,
    input wire [DSIZE-1:0] data_in,

    output reg [2:0] vc_select
);

    parameter MSB_SLOT = 5;
    parameter DSIZE = 1<<MSB_SLOT;
    parameter RRSIZE = 1<<MSB_SLOT-2;
    // xy - 1'b0
    // yx - 1'b1 
    parameter algorithm = 1'b0;
    parameter  [2:0] PORT = 0; 
    parameter  [RRSIZE-1:0] ROUTER_X = 0;
    parameter  [RRSIZE-1:0] ROUTER_Y = 0;




    // Use the flit format if needed later on -> currently going for packet based switching
    // Flit format
    //  0 0 0 0 0 0 B1 B0
    // 11 - Head flit
    // 01 - Body flit
    // 10 - Tail flit

    `define N 3'b000
    `define S 3'b001
    `define E 3'b010
    `define W 3'b011
    `define L 3'b100
    `define INVALID 3'b111
    
    wire [RRSIZE-1:0] dest_x,dest_y;
    
    assign dest_x = data_in[DSIZE-1:DSIZE-RRSIZE]; 
    assign dest_y = data_in[DSIZE-RRSIZE-1:DSIZE-RRSIZE-RRSIZE]; 

    always @ (*)begin
        if ( algorithm == 1'b0 )begin
        // XY algorithm 
        // First send in X direction 
        // Then Y direction
            if (dest_x == ROUTER_X && dest_y == ROUTER_Y)begin
                vc_select = `L;
            end
            else if (dest_x == ROUTER_X)begin
                if(dest_y < ROUTER_Y)begin
                    vc_select = `N;
                end
                else begin
                    vc_select = `S;
                end
            end
            else begin
                if(dest_x > ROUTER_X)begin
                    vc_select = `E;
                end
                else begin
                    vc_select = `W;
                end
            end

            // check if this works to avoid packets be sending back to source 
            if(vc_select == PORT || reset )
                vc_select = `INVALID;
        end
        else begin

            // YX algorithm 
            // First y direction 
            // Then x direction 
            if (dest_x == ROUTER_X && dest_y == ROUTER_Y)begin
                vc_select = `L;
            end
            else if (dest_y == ROUTER_Y)begin
                if(dest_x < ROUTER_X)begin
                    vc_select = `W;
                end
                else begin
                    vc_select = `E;
                end
            end
            else begin
                if(dest_y > ROUTER_Y)begin
                    vc_select = `S;
                end
                else begin
                    vc_select = `N;
                end
            end

            if(vc_select == PORT || reset )
                vc_select = `INVALID;
                
        end
    end


endmodule

input_module/input_controller.v
/*

File:  input_controller.v
Desciption: Responsible for handling input data to the input module. 

Checks if input data is avaialable and virtual channel buffers are available
data to be read. Once the condition is verified sends read signal
to the input side data.
    
Here the buffer empty is a AND of empty of all the virtual channels 

NOTE: Can we make this for each of the buffers , taking into account the vc_select as well
    
*/


module input_controller(
    input clk,
    input reset,
    input wire input_empty,
    input wire buffer_empty,
    output reg input_read
);

    always @ (*)begin
        if (input_empty == 1'b0  && buffer_empty ==1'b1)
            input_read = 1'b1;
        else
            input_read = 1'b0;
    end

endmodule

input_module/input_module.v
/*
File: input_module.v
Descripton: input module that holds input router 
    and 4 VC buffers coresponding to the 4 other directions
    
Assumption : read_en and write_en are synchronous

Decided to go for 32bit (from 10 bit flits) packets rather than flit division 
change this later on if congestion becomes a problem . 
But considering Networks common packet size for all should 
not be a problem - Akilax0

VC buffers are 
32 bit x 32 slots

CAN USE SIGNALS OF FIFO FOR LATER FLOW CONTROL
*/

`include "../../input_module/input_router.v"
`include "../../input_module/input_controller.v"
`include "../../fifo/vc_buffer.v"
`include "../../utils/rr_arbiter.v"
`include "../../utils/demux_1to5.v"
// `include "../../utils/mux_5to1.v"
// `include "../../utils/mux_5to1_64bit.v"

module input_module(
    input wire clk, 
    input wire reset, 
    input wire [DSIZE-1:0] data_in,

    input wire input_empty, // checks if write buffer of NI is not empty
    output wire input_read,

    output wire [DSIZE-1:0] data_out,

    // signal from output side to read from vc_buffers
    input wire read_en,
    
    // check if this is needed to be output
    output wire [2:0] vc_select
    
    // // for output module flow control
    // // [L,W,E,S,N]
    // input wire [4:0] recv_full;
);

    // North -> 3'b000
    // South -> 3'b001
    // East -> 3'b010
    // West -> 3'b011
    // Local -> 3'b100
    `define N 3'b000
    `define S 3'b001
    `define E 3'b010
    `define W 3'b011
    `define L 3'b100
    `define INVALID 3'b111

    parameter MSB_SLOT = 5;
    parameter DSIZE = 1<<MSB_SLOT;
    parameter RRSIZE = 1<<MSB_SLOT-2;

    parameter ADDRSIZE = 5;
    parameter DEPTH = 1<<ADDRSIZE;

    // Assigning straight 0 to avoid defining bit width 
    parameter [2:0] PORT = 0;
    parameter [RRSIZE-1:0] ROUTER_X = 0;
    parameter [RRSIZE-1:0] ROUTER_Y = 0;
    parameter algorithm = 0;

    // signal to check virtual buffers have empty space
    wire buffer_empty;
    wire write_en;
    wire [4:0] read_empty;

    assign buffer_empty = !full_N && !full_S && !full_E && !full_W && !full_L;
    
    // Need to figure a better way for this
    // check vc select signal here should be able to resolve this 
    assign write_en = (vc_select!=`INVALID && !reset && input_empty)? 1'b1 : 1'b0;
    // assign read_empty = !empty_N || !empty_E || !empty_L || !empty_S || !empty_W; 
    
    assign read_empty = {!empty_L,!empty_W,!empty_E,!empty_S,!empty_N}; // 5 request inputs , and with not full 

    // Signals to the module checked
    input_controller controller(
        .clk(clk),
        .reset(reset),
        .input_empty(input_empty),
        .buffer_empty(buffer_empty),
        .input_read(input_read)
    );
    
    // Need a router output to 
    // enable signal
    // Need additional check to not pass back 
    // Only consider as data packets 

    input_router#(.MSB_SLOT(MSB_SLOT),.DSIZE(DSIZE),.RRSIZE(RRSIZE),.algorithm(algorithm),.PORT(PORT),.ROUTER_X(ROUTER_X),.ROUTER_Y(ROUTER_Y)) ir(
        .clk(clk), 
        .reset(reset),
        .data_in(data_in),
        .vc_select(vc_select) // check if this is needed to be output
    );
    
    // signals for the 5 virtual channels
    wire write_en_N, write_en_S, write_en_E, write_en_W;
    wire read_en_N, read_en_S, read_en_E, read_en_W;
    
    wire error_N, error_S,error_E,error_W;
    wire full_N,full_S,full_E,full_W;
    wire empty_N,empty_S,empty_E,empty_W;
    wire [MSB_SLOT-1:0] ocup_N,ocup_S,ocup_E,ocup_W;
    
    wire [2:0] rr_select;

    // // for Local port
    wire write_en_L;
    wire read_en_L;
    wire error_L, full_L, empty_L;
    wire [MSB_SLOT-1:0] ocup_L;
    

    // // Handling data out
    wire [DSIZE-1:0] data_N, data_S,data_E, data_W, data_L;
    
    // write_en is going to be set to 1'b1 . Remove this if write en is going to be conditional
    // This should be discussed
    demux_1to5 write_enable(write_en,vc_select,write_en_N,write_en_S,write_en_E,write_en_W,write_en_L);
    

    demux_1to5 read_enable(read_en,rr_select,read_en_N,read_en_S,read_en_E,read_en_W,read_en_L);
    
    // mux_5to1 full({full_N,full_S,full_E,full_W,full_L},vc_select,full);
    // mux_5to1 empty({empty_N,empty_S,empty_E,empty_W,empty_L},rr_select,empty);
    // mux_5to1 error({error_N,error_S,error_E,error_W,error_L},rr_select,error);

    // mux_5to1_64bit data(data_N,data_S,data_E,data_W,data_L,rr_select,data_out);
    
    // // add  for ocup to check flow control

    vc_buffer #(.MSB_SLOT(MSB_SLOT),.ADDRSIZE(ADDRSIZE),.DSIZE(DSIZE),.DEPTH(DEPTH)) vc_N(
        clk,
        reset,
        write_en_N,
        read_en_N,
        data_in,
        data_N,
        error_N,
        full_N,
        empty_N,
        ocup_N
    );

    vc_buffer #(.MSB_SLOT(MSB_SLOT),.ADDRSIZE(ADDRSIZE),.DSIZE(DSIZE),.DEPTH(DEPTH)) vc_S(
        clk,
        reset,
        write_en_S,
        read_en_S,
        data_in,
        data_S,
        error_S,
        full_S,
        empty_S,
        ocup_S
    );

    vc_buffer #(.MSB_SLOT(MSB_SLOT),.ADDRSIZE(ADDRSIZE),.DSIZE(DSIZE),.DEPTH(DEPTH)) vc_E(
        clk,
        reset,
        write_en_E,
        read_en_E,
        data_in,
        data_E,
        error_E,
        full_E,
        empty_E,
        ocup_E
    );

    vc_buffer #(.MSB_SLOT(MSB_SLOT),.ADDRSIZE(ADDRSIZE),.DSIZE(DSIZE),.DEPTH(DEPTH)) vc_W(
        clk,
        reset,
        write_en_W,
        read_en_W,
        data_in,
        data_W,
        error_W,
        full_W,
        empty_W,
        ocup_W
    );

    vc_buffer #(.MSB_SLOT(MSB_SLOT),.ADDRSIZE(ADDRSIZE),.DSIZE(DSIZE),.DEPTH(DEPTH)) vc_L(
        clk,
        reset,
        write_en_L,
        read_en_L,
        data_in,
        data_L,
        error_L,
        full_L,
        empty_L,
        ocup_L
    );


    rr_arbiter arb(
        clk,
        reset,
        read_empty,  // input wire [4:0] {!empty_L,!empty_W,!empty_E,!empty_S,!empty_N}, // 5 request inputs , and with not full 
        rr_select
    );

endmodule

tb/input_module/input_module_tb.v
`timescale 1ns / 1ps
`include "../../input_module/input_module.v"

module input_module_tb();
    
    reg clk;
    reg reset;
    reg [DSIZE-1:0] data_in;
    reg input_empty;
    reg read_en;
    wire input_read;
    wire [DSIZE-1:0] data_out; 
    
    // check if this is needed to be output
    wire [2:0] vc_select;

    `define N 3'b000
    `define S 3'b001
    `define E 3'b010
    `define W 3'b011
    `define L 3'b100
    `define INVALID 3'b111

    localparam MSB_SLOT = 5;
    localparam DSIZE = 1<<MSB_SLOT;
    localparam RRSIZE = 1<<MSB_SLOT-2;

    localparam ADDRSIZE = 5;
    localparam DEPTH = 1<<ADDRSIZE;

    // input router calculations 
    localparam [2:0] PORT = 3'b000;
    localparam [RRSIZE-1:0] ROUTER_X = 1;
    localparam [RRSIZE-1:0] ROUTER_Y = 1;
    localparam algorithm = 0;

    // Instantiate the router module
    input_module #(.MSB_SLOT(MSB_SLOT),.DSIZE(DSIZE),.RRSIZE(RRSIZE),.ADDRSIZE(ADDRSIZE),.DEPTH(DEPTH),.PORT(PORT),.ROUTER_X(ROUTER_X),.ROUTER_Y(ROUTER_Y),.algorithm(algorithm)) im (
        .clk(clk),
        .reset(reset),
        .data_in(data_in),
        .input_empty(input_empty),
        .input_read(input_read),
        .data_out(data_out),
        .read_en(read_en),
        .vc_select(vc_select)
    );

    integer i;
    // VCD dump file
    initial begin
        $dumpfile("input_module_tb.vcd");
        $dumpvars(0, input_module_tb);

        // Initialize signals
        clk = 1;
        reset = 1;

        data_in = 32'h00000000;
        input_empty = 1'b0;
        read_en = 1'b0;

        #20;
        // Release reset
        reset = 0;

        data_in = 32'h01020001;
        input_empty = 1'b1;
        read_en = 1'b0;
        //South

        #20;
        data_in = 32'h00010001;
        input_empty = 1'b1;
        read_en = 1'b0;
        // West
        //
        #20;
        input_empty = 1'b0;
        read_en = 1'b1;

        #20;
        input_empty = 1'b0;
        read_en = 1'b1;

        #20;
        input_empty = 1'b0;
        read_en = 1'b1;

        #20;
        input_empty = 1'b0;
        read_en = 1'b1;
        
        
        // data_in = 32'h01000001;
        // input_empty = 1'b1;
        // read_en = 1'b0;
        // // North but same port

        // #20;

        // data_in = 32'h01020001;
        // input_empty = 1'b1;
        // read_en = 1'b0;
        // //South

        // #20;
        // data_in = 32'h00010001;
        // input_empty = 1'b1;
        // read_en = 1'b0;
        // // West

        // #20;

        // data_in = 32'h01020002;
        // input_empty = 1'b1;
        // read_en = 1'b0;
        // //South

        #20;

        
        input_empty = 1'b0;


        // #20;
        // data_in = 32'h01020002;
        // input_empty = 1'b0;
        // read_en = 1'b1;
        // // East


        // #20;
        // data_in = 32'h02010001;
        // input_empty = 1'b1;
        // read_en = 1'b0;
        // // East

        // #20;
        // data_in = 32'h02010001;
        // input_empty = 1'b1;
        // read_en = 1'b1;
        // // East

        #40;
        reset = 0;
        // Perform additional read and write operations as needed
        // End simulation
        $finish;
    end

    // Clock generation
    always begin
        #5 clk = ~clk;
    end

endmodule

tb/input_module/input_module_tb.vcd
$date
	Sat Mar  9 10:44:48 2024
$end
$version
	Icarus Verilog
$end
$timescale
	1ps
$end
$scope module input_module_tb $end
$var wire 32 ! data_out [31:0] $end
$var wire 3 " vc_select [2:0] $end
$var wire 1 # input_read $end
$var reg 1 $ clk $end
$var reg 32 % data_in [31:0] $end
$var reg 1 & input_empty $end
$var reg 1 ' read_en $end
$var reg 1 ( reset $end
$scope module im $end
$var wire 1 ) buffer_empty $end
$var wire 1 $ clk $end
$var wire 32 * data_in [31:0] $end
$var wire 32 + data_out [31:0] $end
$var wire 1 & input_empty $end
$var wire 1 ' read_en $end
$var wire 1 ( reset $end
$var wire 1 , write_en_W $end
$var wire 1 - write_en_S $end
$var wire 1 . write_en_N $end
$var wire 1 / write_en_L $end
$var wire 1 0 write_en_E $end
$var wire 1 1 write_en $end
$var wire 3 2 vc_select [2:0] $end
$var wire 3 3 rr_select [2:0] $end
$var wire 1 4 read_en_W $end
$var wire 1 5 read_en_S $end
$var wire 1 6 read_en_N $end
$var wire 1 7 read_en_L $end
$var wire 1 8 read_en_E $end
$var wire 5 9 read_empty [4:0] $end
$var wire 5 : ocup_W [4:0] $end
$var wire 5 ; ocup_S [4:0] $end
$var wire 5 < ocup_N [4:0] $end
$var wire 5 = ocup_L [4:0] $end
$var wire 5 > ocup_E [4:0] $end
$var wire 1 # input_read $end
$var wire 1 ? full_W $end
$var wire 1 @ full_S $end
$var wire 1 A full_N $end
$var wire 1 B full_L $end
$var wire 1 C full_E $end
$var wire 1 D error_W $end
$var wire 1 E error_S $end
$var wire 1 F error_N $end
$var wire 1 G error_L $end
$var wire 1 H error_E $end
$var wire 1 I empty_W $end
$var wire 1 J empty_S $end
$var wire 1 K empty_N $end
$var wire 1 L empty_L $end
$var wire 1 M empty_E $end
$var wire 32 N data_W [31:0] $end
$var wire 32 O data_S [31:0] $end
$var wire 32 P data_N [31:0] $end
$var wire 32 Q data_L [31:0] $end
$var wire 32 R data_E [31:0] $end
$scope module arb $end
$var wire 1 $ clk $end
$var wire 5 S request [4:0] $end
$var wire 1 ( reset $end
$var reg 3 T grant [2:0] $end
$var reg 3 U next_state [2:0] $end
$var reg 3 V state [2:0] $end
$upscope $end
$scope module controller $end
$var wire 1 ) buffer_empty $end
$var wire 1 $ clk $end
$var wire 1 & input_empty $end
$var wire 1 ( reset $end
$var reg 1 # input_read $end
$upscope $end
$scope module ir $end
$var wire 1 $ clk $end
$var wire 32 W data_in [31:0] $end
$var wire 1 ( reset $end
$var wire 8 X dest_y [7:0] $end
$var wire 8 Y dest_x [7:0] $end
$var reg 3 Z vc_select [2:0] $end
$upscope $end
$scope module read_enable $end
$var wire 3 [ ctrl [2:0] $end
$var wire 1 ' data_input $end
$var wire 1 7 out4 $end
$var wire 1 4 out3 $end
$var wire 1 8 out2 $end
$var wire 1 5 out1 $end
$var wire 1 6 out0 $end
$upscope $end
$scope module vc_E $end
$var wire 1 $ clk $end
$var wire 32 \ data_in [31:0] $end
$var wire 1 8 read_en $end
$var wire 1 ( reset $end
$var wire 1 0 write_en $end
$var reg 32 ] data_out [31:0] $end
$var reg 1 M empty $end
$var reg 1 H error $end
$var reg 6 ^ fifo_ocup [5:0] $end
$var reg 1 C full $end
$var reg 6 _ next_read_ptr [5:0] $end
$var reg 6 ` next_write_ptr [5:0] $end
$var reg 5 a ocup [4:0] $end
$var reg 6 b read_ptr_ff [5:0] $end
$var reg 6 c write_ptr_ff [5:0] $end
$var integer 32 d i [31:0] $end
$upscope $end
$scope module vc_L $end
$var wire 1 $ clk $end
$var wire 32 e data_in [31:0] $end
$var wire 1 7 read_en $end
$var wire 1 ( reset $end
$var wire 1 / write_en $end
$var reg 32 f data_out [31:0] $end
$var reg 1 L empty $end
$var reg 1 G error $end
$var reg 6 g fifo_ocup [5:0] $end
$var reg 1 B full $end
$var reg 6 h next_read_ptr [5:0] $end
$var reg 6 i next_write_ptr [5:0] $end
$var reg 5 j ocup [4:0] $end
$var reg 6 k read_ptr_ff [5:0] $end
$var reg 6 l write_ptr_ff [5:0] $end
$var integer 32 m i [31:0] $end
$upscope $end
$scope module vc_N $end
$var wire 1 $ clk $end
$var wire 32 n data_in [31:0] $end
$var wire 1 6 read_en $end
$var wire 1 ( reset $end
$var wire 1 . write_en $end
$var reg 32 o data_out [31:0] $end
$var reg 1 K empty $end
$var reg 1 F error $end
$var reg 6 p fifo_ocup [5:0] $end
$var reg 1 A full $end
$var reg 6 q next_read_ptr [5:0] $end
$var reg 6 r next_write_ptr [5:0] $end
$var reg 5 s ocup [4:0] $end
$var reg 6 t read_ptr_ff [5:0] $end
$var reg 6 u write_ptr_ff [5:0] $end
$var integer 32 v i [31:0] $end
$upscope $end
$scope module vc_S $end
$var wire 1 $ clk $end
$var wire 32 w data_in [31:0] $end
$var wire 1 5 read_en $end
$var wire 1 ( reset $end
$var wire 1 - write_en $end
$var reg 32 x data_out [31:0] $end
$var reg 1 J empty $end
$var reg 1 E error $end
$var reg 6 y fifo_ocup [5:0] $end
$var reg 1 @ full $end
$var reg 6 z next_read_ptr [5:0] $end
$var reg 6 { next_write_ptr [5:0] $end
$var reg 5 | ocup [4:0] $end
$var reg 6 } read_ptr_ff [5:0] $end
$var reg 6 ~ write_ptr_ff [5:0] $end
$var integer 32 !" i [31:0] $end
$upscope $end
$scope module vc_W $end
$var wire 1 $ clk $end
$var wire 32 "" data_in [31:0] $end
$var wire 1 4 read_en $end
$var wire 1 ( reset $end
$var wire 1 , write_en $end
$var reg 32 #" data_out [31:0] $end
$var reg 1 I empty $end
$var reg 1 D error $end
$var reg 6 $" fifo_ocup [5:0] $end
$var reg 1 ? full $end
$var reg 6 %" next_read_ptr [5:0] $end
$var reg 6 &" next_write_ptr [5:0] $end
$var reg 5 '" ocup [4:0] $end
$var reg 6 (" read_ptr_ff [5:0] $end
$var reg 6 )" write_ptr_ff [5:0] $end
$var integer 32 *" i [31:0] $end
$upscope $end
$scope module write_enable $end
$var wire 3 +" ctrl [2:0] $end
$var wire 1 1 data_input $end
$var wire 1 / out4 $end
$var wire 1 , out3 $end
$var wire 1 0 out2 $end
$var wire 1 - out1 $end
$var wire 1 . out0 $end
$upscope $end
$upscope $end
$upscope $end
$enddefinitions $end
#0
$dumpvars
b111 +"
b100000 *"
b0 )"
b0 ("
b0 '"
b0 &"
b0 %"
b0 $"
b0 #"
b0 ""
b100000 !"
b0 ~
b0 }
b0 |
b0 {
b0 z
b0 y
b0 x
b0 w
b100000 v
b0 u
b0 t
b0 s
b0 r
b0 q
b0 p
b0 o
b0 n
b100000 m
b0 l
b0 k
b0 j
b0 i
b0 h
b0 g
b0 f
b0 e
b100000 d
b0 c
b0 b
b0 a
b0 `
b0 _
b0 ^
b0 ]
b0 \
b111 [
b111 Z
b0 Y
b0 X
b0 W
b101 V
b101 U
b111 T
b0 S
b0 R
b0 Q
b0 P
b0 O
b0 N
1M
1L
1K
1J
1I
0H
0G
0F
0E
0D
0C
0B
0A
0@
0?
b0 >
b0 =
b0 <
b0 ;
b0 :
b0 9
08
07
06
05
04
b111 3
b111 2
01
00
0/
0.
0-
0,
bz +
b0 *
1)
1(
0'
0&
b0 %
1$
1#
b111 "
bz !
$end
#5000
0$
#10000
b100000 m
b100000 *"
b100000 d
b100000 !"
b100000 v
1$
#15000
0$
#20000
b1 {
1-
11
0#
b1 Y
b10 X
b1 "
b1 2
b1 Z
b1 +"
1$
1&
b1000000100000000000000001 %
b1000000100000000000000001 *
b1000000100000000000000001 W
b1000000100000000000000001 \
b1000000100000000000000001 e
b1000000100000000000000001 n
b1000000100000000000000001 w
b1000000100000000000000001 ""
0(
#25000
0$
#30000
b1 U
b1 ;
b1 |
b1 y
b10 {
b1000000100000000000000001 O
b1000000100000000000000001 x
b10 9
b10 S
0J
b1 ~
1$
#35000
0$
#40000
b10 ;
b10 |
b10 y
b1 3
b1 T
b1 [
b10 ~
b1 V
b10 {
b1 &"
0-
1,
b11 "
b11 2
b11 Z
b11 +"
b0 Y
b1 X
1$
b10000000000000001 %
b10000000000000001 *
b10000000000000001 W
b10000000000000001 \
b10000000000000001 e
b10000000000000001 n
b10000000000000001 w
b10000000000000001 ""
#45000
0$
#50000
b11 U
b1 :
b1 '"
b1 $"
b10 &"
b10000000000000001 N
b10000000000000001 #"
b1010 9
b1010 S
0I
b1 )"
1$
#55000
0$
#60000
b1 %"
14
b10 :
b10 '"
b10 $"
b11 3
b11 T
b11 [
b10 )"
b11 V
b10 &"
0,
b0 z
01
05
1#
1$
1'
0&
#65000
0$
#70000
b1 :
b1 '"
b1 $"
b10 %"
b1 ("
1$
#75000
0$
#80000
b1 U
b0 :
b0 '"
b0 $"
1D
b0 N
b0 #"
b10 9
b10 S
1I
b10 ("
1$
#85000
0$
#90000
b1 z
0D
15
04
b1 3
b1 T
b1 [
b1 V
1$
#95000
0$
#100000
b1 ;
b1 |
b1 y
b10 z
b10000000000000001 O
b10000000000000001 x
b1 }
1$
#105000
0$
#110000
b101 U
b0 ;
b0 |
b0 y
1E
b0 O
b0 x
b0 9
b0 S
1J
b10 }
1$
#115000
0$
#120000
0E
05
b111 3
b111 T
b111 [
b101 V
1$
