ni/fifo_32x64.v
module fifo_32x64(
    input wire clk,        // Clock signal
    input wire reset,      // Reset signal

    input wire write_en,   // Write enable signal
    input wire read_en,    // Read enable signal

    input wire [63:0] data_in, // Data input (64 bits wide)
    output reg [63:0] data_out, // Data output (64 bits wide)

    output wire full,      // Full flag
    output wire empty,      // Empty flag

    // nhandle this appropriately 
    output wire thresh
);

  // fifo module to store addr + data for network write read

  // Define FIFO parameters
  parameter FIFO_DEPTH = 32;
  parameter DATA_WIDTH = 64;

  // Internal FIFO storage
  reg [DATA_WIDTH-1:0] fifo [0:FIFO_DEPTH-1];
  reg [4:0] wr_ptr; // Write pointer
  reg [4:0] rd_ptr; // Read pointer
  wire [4:0] count = wr_ptr - rd_ptr;

  // Full and empty flags
  assign full = (count == FIFO_DEPTH);
  assign empty = (count == 0);

  // Write and read logic
  always @(posedge clk or posedge reset) begin
    if (reset) begin
      wr_ptr <= 5'b0;
      rd_ptr <= 5'b0;
    end 
    else begin
      if (write_en && !full) begin
        fifo[wr_ptr] <= data_in;
        wr_ptr <= wr_ptr + 1;
      end

      if (read_en && !empty) begin
        data_out <= fifo[rd_ptr];
        rd_ptr <= rd_ptr + 1;
      end
    end
  end

endmodule

tb/fifo_tb.v
`timescale 1ns / 1ps
`include "../ni/fifo_32x64.v"

module fifo_tb();

    // Define testbench signals
    reg clk;
    reg reset;
    reg write_en;
    reg read_en;
    reg [63:0] data_in;
    wire [63:0] data_out;
    wire full;
    wire empty;

    // Instantiate the FIFO module
    fifo_32x64 my_fifo (
        .clk(clk),
        .reset(reset),
        .write_en(write_en),
        .read_en(read_en),
        .data_in(data_in),
        .data_out(data_out),
        .full(full),
        .empty(empty)
    );

    // VCD dump file
    initial begin
        $dumpfile("fifo_tb.vcd");
        $dumpvars(0, fifo_tb);

        // Initialize signals
        clk = 0;
        reset = 1;
        write_en = 0;
        read_en = 0;
        data_in = 64'h0;

        #20;
        // Release reset
        reset = 1'b0;
        // Write data to the FIFO
        write_en = 1;
        data_in = 64'hA5A5A5A5A5A5A5A5; // Example data
        #10;
        // Release reset
        reset = 1'b0;
        // Write data to the FIFO
        write_en = 1;
        data_in = 64'hA5A5A5A5A5A5A5A5; // Example data

        #10;
        // Release reset
        reset = 1'b0;
        // Write data to the FIFO
        write_en = 1;
        data_in = 64'hA5A5A5A5A5A5A1A5; // Example data

        #10;
        // Release reset
        reset = 1'b0;
        // Write data to the FIFO
        write_en = 1;
        data_in = 64'hA5A5A5A5A5A5A4A5; // Example data

        #10;
        // Release reset
        reset = 1'b0;
        // Write data to the FIFO
        write_en = 1;
        data_in = 64'h35A5A5A5A5A5A5A5; // Example data

        #10;
        write_en = 0;
        // Read data from the FIFO
        read_en = 1;

        #10;
        // Perform additional read and write operations as needed
        // End simulation
        $finish;
    end

    // Clock generation
    always begin
        #5 clk = ~clk;
    end

endmodule

tb/fifo_tb.vcd
$date
	Thu Oct 26 09:32:30 2023
$end
$version
	Icarus Verilog
$end
$timescale
	1ps
$end
$scope module fifo_tb $end
$var wire 1 ! full $end
$var wire 1 " empty $end
$var wire 64 # data_out [63:0] $end
$var reg 1 $ clk $end
$var reg 64 % data_in [63:0] $end
$var reg 1 & read_en $end
$var reg 1 ' reset $end
$var reg 1 ( write_en $end
$scope module my_fifo $end
$var wire 1 $ clk $end
$var wire 64 ) data_in [63:0] $end
$var wire 1 & read_en $end
$var wire 1 ' reset $end
$var wire 1 * thresh $end
$var wire 1 ( write_en $end
$var wire 1 ! full $end
$var wire 1 " empty $end
$var wire 5 + count [4:0] $end
$var reg 64 , data_out [63:0] $end
$var reg 5 - rd_ptr [4:0] $end
$var reg 5 . wr_ptr [4:0] $end
$upscope $end
$upscope $end
$enddefinitions $end
#0
$dumpvars
b0 .
b0 -
bx ,
b0 +
z*
b0 )
0(
1'
0&
b0 %
0$
bx #
1"
0!
$end
#5000
1$
#10000
0$
#15000
1$
#20000
0$
b1010010110100101101001011010010110100101101001011010010110100101 %
b1010010110100101101001011010010110100101101001011010010110100101 )
1(
0'
#25000
0"
b1 +
b1 .
1$
#30000
0$
#35000
b10 +
b10 .
1$
#40000
0$
b1010010110100101101001011010010110100101101001011010000110100101 %
b1010010110100101101001011010010110100101101001011010000110100101 )
#45000
b11 +
b11 .
1$
#50000
0$
b1010010110100101101001011010010110100101101001011010010010100101 %
b1010010110100101101001011010010110100101101001011010010010100101 )
#55000
b100 +
b100 .
1$
#60000
0$
b11010110100101101001011010010110100101101001011010010110100101 %
b11010110100101101001011010010110100101101001011010010110100101 )
#65000
b101 +
b101 .
1$
#70000
0$
1&
0(
#75000
b100 +
b1 -
b1010010110100101101001011010010110100101101001011010010110100101 #
b1010010110100101101001011010010110100101101001011010010110100101 ,
1$
